<?xml version="1.0" encoding="utf-8" standalone="yes"?>
<dictionary>
  <key>FALLA</key>
  <value>
    <collection>
      <itemcol>
        <word>FALLA</word>
        <filepath>\\192.168.2.2\00 - Departments\Common\Quality - Calidad\13 SSyPA - HSE\Formatos Seguridad\145.PS007.F07 Reporte de Falla Operativa- Failure Report  R.00 (21-Oct-1....docx</filepath>
        <Paragraphs>ORMACION DE  LA FALLA        Failure Description Descripci n de la Falla                 Actions Performed Acciones Correctivas                       </Paragraphs>
      </itemcol>
      <itemcol>
        <word>FALLA</word>
        <filepath>\\192.168.2.2\00 - Departments\Common\scan\chiefofficer.3027\SEGURIDAD\10.-OCTUBRE\8,9 &amp; 10 men down, fire, abandon\1.- Planeacion colision de choper.doc</filepath>
        <Paragraphs>PCOTERO REPORTA FALLA MECANICA Y REALIZA MANIOBRA PARA ATERRIZAJE  COLISIONANDO  CON ESTRUCTURA DE HELIPUERTO  PROVOCANDO INCENDIO NO CONTROLADO Y POS</Paragraphs>
      </itemcol>
      <itemcol>
        <word>FALLA</word>
        <filepath>\\192.168.2.2\00 - Departments\Common\SOC Cards\SOC Tours\11.- NOVIEMBRE\2.- CAFERERIA UP DECK D.pdf</filepath>
        <Paragraphs>22 :00 HRS NOVEMBER 2 st , 2014 FALLA DE VALVULA DE FUENTE DE SODAS </Paragraphs>
      </itemcol>
    </collection>
  </value>
  <key>FALTA</key>
  <value>
    <collection>
      <itemcol>
        <word>FALTA</word>
        <filepath>\\192.168.2.2\00 - Departments\Common\scan\captain.3027\SOC Tours\08.- AGOSTO\09 Heavy tool store @ drill floor.pdf</filepath>
        <Paragraphs>FALTA DE ORDEN Y LIMPIEZA </Paragraphs>
      </itemcol>
      <itemcol>
        <word>FALTA</word>
        <filepath>\\192.168.2.2\00 - Departments\Common\scan\captain.3027\SOC Tours\08.- AGOSTO\11 DATS'skid Starboard side.pdf</filepath>
        <Paragraphs>FALTA DE ORDEN Y LIMPIEZA (CORREGIDO) </Paragraphs>
      </itemcol>
      <itemcol>
        <word>FALTA</word>
        <filepath>\\192.168.2.2\00 - Departments\Common\scan\captain.3027\SOC Tours\08.- AGOSTO\11 MOON POOL.pdf</filepath>
        <Paragraphs>FALTA ORDEN  DE MATERIAL  </Paragraphs>
      </itemcol>
      <itemcol>
        <word>FALTA</word>
        <filepath>\\192.168.2.2\00 - Departments\Common\scan\captain.3027\SOC Tours\08.- AGOSTO\17 All AEREAS.pdf</filepath>
        <Paragraphs>FALTA LIMPIEZA </Paragraphs>
      </itemcol>
      <itemcol>
        <word>FALTA</word>
        <filepath>\\192.168.2.2\00 - Departments\Common\scan\captain.3027\SOC Tours\08.- AGOSTO\18 INCINERATOR ROOM.pdf</filepath>
        <Paragraphs>UST   th        FALTA REJILLA O  BARRERAS RESTRICTIVAS </Paragraphs>
      </itemcol>
      <itemcol>
        <word>FALTA</word>
        <filepath>\\192.168.2.2\00 - Departments\Common\scan\captain.3027\SOC Tours\08.- AGOSTO\26 Cement room.pdf</filepath>
        <Paragraphs>FALTA DE  ORDEN Y LIMPIEZA </Paragraphs>
      </itemcol>
      <itemcol>
        <word>FALTA</word>
        <filepath>\\192.168.2.2\00 - Departments\Common\scan\captain.3027\SOC Tours\08.- AGOSTO\30 Engine room #1.pdf</filepath>
        <Paragraphs>REMAINS OF WOODEN BOX SCATTERED  FALTA DE ORDEN (CORREGIDA) </Paragraphs>
      </itemcol>
      <itemcol>
        <word>FALTA</word>
        <filepath>\\192.168.2.2\00 - Departments\Common\scan\captain.3027\SOC Tours\2014\01.- ENERO\26 ENE 2013 SUB SEA.pdf</filepath>
        <Paragraphs>V  SOC CARD TOUR                        SUB SEA AREA                           26 Enero del        FALTA SE321ALAMIENTOS A CONTENEDORES</Paragraphs>
      </itemcol>
      <itemcol>
        <word>FALTA</word>
        <filepath>\\192.168.2.2\00 - Departments\Common\scan\captain.3027\SOC Tours\2014\01.- ENERO\28 ENE 2013 PISO DE PERFORACION.pdf</filepath>
        <Paragraphs>V  SOC CARD TOUR                        PISO DE PERFORACION           28 Enero del 2014  FALTA PINTAR  OBSTACULO, PARA MEJOR IDENTIFICA-</Paragraphs>
      </itemcol>
      <itemcol>
        <word>FALTA</word>
        <filepath>\\192.168.2.2\00 - Departments\Common\scan\captain.3027\SOC Tours\2014\01.- ENERO\29 ENE 2014  t. soldadura .pdf</filepath>
        <Paragraphs>V  SOC CARD TOUR                        TALLER DE SOLDADURA                29 Enero del 2014 FALTA ORDEN Y LIMPIEZA EN GENERAL</Paragraphs>
      </itemcol>
      <itemcol>
        <word>FALTA</word>
        <filepath>\\192.168.2.2\00 - Departments\Common\scan\captain.3027\SOC Tours\2014\01.- ENERO\29 ENE 2014 Talleres.pdf</filepath>
        <Paragraphs>V  SOC CARD TOUR                                   29 Enero del 2014        FALTA  ORDEN Y LIMPIEZA</Paragraphs>
      </itemcol>
      <itemcol>
        <word>FALTA</word>
        <filepath>\\192.168.2.2\00 - Departments\Common\scan\captain.3027\SOC Tours\2014\01.- ENERO\30 ENE 2014 cubierta.pdf</filepath>
        <Paragraphs>FALTA DEPURAR AREA DE RESIDUOS  E </Paragraphs>
      </itemcol>
      <itemcol>
        <word>FALTA</word>
        <filepath>\\192.168.2.2\00 - Departments\Common\scan\captain.3027\SOC Tours\2014\01.- ENERO\31 ENE 2014 CTO. BOMBAS.pdf</filepath>
        <Paragraphs>FALTA DE ORDEN Y LIMPIEZA</Paragraphs>
      </itemcol>
      <itemcol>
        <word>FALTA</word>
        <filepath>\\192.168.2.2\00 - Departments\Common\scan\captain.3027\SOC Tours\2014\01.- ENERO\Stop Turs.pdf</filepath>
        <Paragraphs>      TAPA DE POCETO FUERA DE LUGAR       FALTA SE361ALAMIENTO DE  RUTA DE EVA-</Paragraphs>
      </itemcol>
      <itemcol>
        <word>FALTA</word>
        <filepath>\\192.168.2.2\00 - Departments\Common\scan\captain.3027\SOC Tours\2014\02.- FEBRERO\01 FEB 2014  COLUM, PROA ESTR.pdf</filepath>
        <Paragraphs>FALTA DE ORDEN Y LIMPIEZA</Paragraphs>
      </itemcol>
      <itemcol>
        <word>FALTA</word>
        <filepath>\\192.168.2.2\00 - Departments\Common\scan\captain.3027\SOC Tours\2014\02.- FEBRERO\02 FEB 2014  INCINERADOR.pdf</filepath>
        <Paragraphs>FALTA SE321ALAMIENTO DE SUPERFICIES CA-</Paragraphs>
      </itemcol>
      <itemcol>
        <word>FALTA</word>
        <filepath>\\192.168.2.2\00 - Departments\Common\scan\captain.3027\SOC Tours\2014\02.- FEBRERO\03 FEB 2014 COLUM. POPA ESTR .pdf</filepath>
        <Paragraphs>FALTA DE ORDEN Y LIMPIEZA (COLUMNA </Paragraphs>
      </itemcol>
      <itemcol>
        <word>FALTA</word>
        <filepath>\\192.168.2.2\00 - Departments\Common\scan\captain.3027\SOC Tours\2014\02.- FEBRERO\06 FEB 2014 - .pdf</filepath>
        <Paragraphs>V  Safety findings                      Cubierta / Proa          06 DE FEBRERO DEL 2014  FALTA FIJAR COMPRESOR DE LA                </Paragraphs>
      </itemcol>
      <itemcol>
        <word>FALTA</word>
        <filepath>\\192.168.2.2\00 - Departments\Common\scan\captain.3027\SOC Tours\2014\02.- FEBRERO\06 FEB 2014 2200.pdf</filepath>
        <Paragraphs>V  Safety findings                      Temblorinas          06 DE FEBRERO DEL 2014 FALTA ORDEN Y LIMPIEZA</Paragraphs>
      </itemcol>
      <itemcol>
        <word>FALTA</word>
        <filepath>\\192.168.2.2\00 - Departments\Common\scan\captain.3027\SOC Tours\2014\02.- FEBRERO\07 FEB 2014 .pdf</filepath>
        <Paragraphs>V  Safety Tour                   TWEEN DECK CUARTO DE COMPRESORES DE SERVICIO LADO BABOR  07 DE FEBRERO DEL 2014TRA INCOMPLETO, FALTA LA FIRMA DE UNA </Paragraphs>
      </itemcol>
      <itemcol>
        <word>FALTA</word>
        <filepath>\\192.168.2.2\00 - Departments\Common\scan\captain.3027\SOC Tours\2014\02.- FEBRERO\07 FEB 2014 2200 .pdf</filepath>
        <Paragraphs>HACE FALTA LIMPIEZA</Paragraphs>
      </itemcol>
      <itemcol>
        <word>FALTA</word>
        <filepath>\\192.168.2.2\00 - Departments\Common\scan\captain.3027\SOC Tours\2014\02.- FEBRERO\08 FEB 2014 HELIDECK.pdf</filepath>
        <Paragraphs>FALTA COLOCAR MARCHAMO (COLA DE RATA) EN </Paragraphs>
      </itemcol>
      <itemcol>
        <word>FALTA</word>
        <filepath>\\192.168.2.2\00 - Departments\Common\scan\captain.3027\SOC Tours\2014\02.- FEBRERO\09 FEB 2014 1000.pdf</filepath>
        <Paragraphs>INCORRECT STORAGE OF LADDER HACE FALTA ORGANIZACION DE MATERIALES Y </Paragraphs>
      </itemcol>
      <itemcol>
        <word>FALTA</word>
        <filepath>\\192.168.2.2\00 - Departments\Common\scan\captain.3027\SOC Tours\2014\02.- FEBRERO\10 FEB 2014 1000.pdf</filepath>
        <Paragraphs>FIRE WATHMAN  AWAY FROM FIRE EXTINGUISHER FALTA PLACA PARA EVITAR CAIDAS</Paragraphs>
      </itemcol>
      <itemcol>
        <word>FALTA</word>
        <filepath>\\192.168.2.2\00 - Departments\Common\scan\captain.3027\SOC Tours\2014\02.- FEBRERO\10 FEB 2014 2200.pdf</filepath>
        <Paragraphs>V  Safety Tour                   TALLER DE TORNO/LATHE WORKSHOP 2200 HRS 10 DE FEBRERO DE 2014         HACE FALTA LETRERO DE SEGURIDAD SOBRE </Paragraphs>
      </itemcol>
      <itemcol>
        <word>FALTA</word>
        <filepath>\\192.168.2.2\00 - Departments\Common\scan\captain.3027\SOC Tours\2014\02.- FEBRERO\11 FEB 2014 1000.pdf</filepath>
        <Paragraphs>WORK AREA WITH RISK OF CHEMICAL POLLUTION FALTA DE ORDEN Y LIMPIEZA TUNEL DE PONTOON  </Paragraphs>
      </itemcol>
      <itemcol>
        <word>FALTA</word>
        <filepath>\\192.168.2.2\00 - Departments\Common\scan\captain.3027\SOC Tours\2014\02.- FEBRERO\11 FEB 2014 2200.pdf</filepath>
        <Paragraphs>V  Safety Tour                   TALLER DE SOLDADURA/WELDING SHOP  22:00 HRS 11 DE FEBRERO DE 2014 FALTA DE ORDEN Y LIMPIEZA TUNEL DE PONTOON  </Paragraphs>
      </itemcol>
      <itemcol>
        <word>FALTA</word>
        <filepath>\\192.168.2.2\00 - Departments\Common\scan\captain.3027\SOC Tours\2014\02.- FEBRERO\12 FEB 2014 1000.pdf</filepath>
        <Paragraphs>OBJECT WITHOUT INDICATING THE RISK TO CLIMB. FALTA ORDEN Y LIMPIEZA/</Paragraphs>
      </itemcol>
      <itemcol>
        <word>FALTA</word>
        <filepath>\\192.168.2.2\00 - Departments\Common\scan\captain.3027\SOC Tours\2014\02.- FEBRERO\13 FEB 2014 2200.pdf</filepath>
        <Paragraphs>TOP OF CONTAINER NEEDS SOME CLEANING FALTA PROCEDIMIENTO EN ESPA321OL DE  </Paragraphs>
      </itemcol>
      <itemcol>
        <word>FALTA</word>
        <filepath>\\192.168.2.2\00 - Departments\Common\scan\captain.3027\SOC Tours\2014\02.- FEBRERO\14 FEB 2014 1000 .pdf</filepath>
        <Paragraphs>10:00 HRS 14  DE FEBRERO DE 2014         FALTA SE321ALIZAR LA RUTA DE ESCAPE  </Paragraphs>
      </itemcol>
      <itemcol>
        <word>FALTA</word>
        <filepath>\\192.168.2.2\00 - Departments\Common\scan\captain.3027\SOC Tours\2014\02.- FEBRERO\15 FEB 2014 1000 .pdf</filepath>
        <Paragraphs>INSURED IN BLOCK CHAIN CABLE CHANNEL FALTA MICA PROTECTORA</Paragraphs>
      </itemcol>
      <itemcol>
        <word>FALTA</word>
        <filepath>\\192.168.2.2\00 - Departments\Common\scan\captain.3027\SOC Tours\2014\02.- FEBRERO\16 FEB 2014 1000.pdf</filepath>
        <Paragraphs>NOT SUITABLE CONTAINER MARKED (ENGINE ROOM #2) FALTA UN TAPETE ENTRE EL CILINDRO Y EL PISO</Paragraphs>
      </itemcol>
      <itemcol>
        <word>FALTA</word>
        <filepath>\\192.168.2.2\00 - Departments\Common\scan\captain.3027\SOC Tours\2014\02.- FEBRERO\17 FEB 2014 2200.pdf</filepath>
        <Paragraphs>         PPE NEEDS A DESIGNATED STORAGE PLACE         HACE FALTA LIMPIEZA DE PISO. . </Paragraphs>
      </itemcol>
      <itemcol>
        <word>FALTA</word>
        <filepath>\\192.168.2.2\00 - Departments\Common\scan\captain.3027\SOC Tours\2014\02.- FEBRERO\18 FEB 2014 1000.pdf</filepath>
        <Paragraphs>DE SEGURIDAD. FALTA ORDEN Y LIMPIEZA BUENA PRACTICA EN ALMACENAJE DE </Paragraphs>
      </itemcol>
      <itemcol>
        <word>FALTA</word>
        <filepath>\\192.168.2.2\00 - Departments\Common\scan\captain.3027\SOC Tours\2014\02.- FEBRERO\19 FEB 2014 1000.pdf</filepath>
        <Paragraphs>           FALTA ORDEN Y LIMPIEZA. </Paragraphs>
      </itemcol>
      <itemcol>
        <word>FALTA</word>
        <filepath>\\192.168.2.2\00 - Departments\Common\scan\captain.3027\SOC Tours\2014\02.- FEBRERO\19 FEB 2014 2200.pdf</filepath>
        <Paragraphs>  FALTA CINTA BARRICADA APROPIADA . </Paragraphs>
      </itemcol>
      <itemcol>
        <word>FALTA</word>
        <filepath>\\192.168.2.2\00 - Departments\Common\scan\captain.3027\SOC Tours\2014\02.- FEBRERO\23 FEB 2014 1000.pdf</filepath>
        <Paragraphs>22:00 HRS 23 DE FEBRERO DE 2014  FALTA EXTINTOR EN MONTACARGAS</Paragraphs>
      </itemcol>
      <itemcol>
        <word>FALTA</word>
        <filepath>\\192.168.2.2\00 - Departments\Common\scan\captain.3027\SOC Tours\2014\03.- MARZO\01 MAR 2014 2200.pdf</filepath>
        <Paragraphs>FALTA LETRERO ALTO VOLTAJE</Paragraphs>
      </itemcol>
      <itemcol>
        <word>FALTA</word>
        <filepath>\\192.168.2.2\00 - Departments\Common\scan\captain.3027\SOC Tours\2014\03.- MARZO\10 MAR 2014 1000.pdf</filepath>
        <Paragraphs>FALTA PASADOR EN PASAMANOS</Paragraphs>
      </itemcol>
      <itemcol>
        <word>FALTA</word>
        <filepath>\\192.168.2.2\00 - Departments\Common\scan\captain.3027\SOC Tours\2014\03.- MARZO\14 MAR 2014 1000.pdf</filepath>
        <Paragraphs>FALTA DE ROMBO DE SEGURIDAD</Paragraphs>
      </itemcol>
      <itemcol>
        <word>FALTA</word>
        <filepath>\\192.168.2.2\00 - Departments\Common\scan\captain.3027\SOC Tours\2014\03.- MARZO\17 MAR 2014 2200 Drilling Tools Shop.pdf</filepath>
        <Paragraphs>V  Safety Tour            DRILLING TOOLS SHOP               22:00 HRS MARCH 17h 2014 FALTA ORDEN Y LIMPIEZA</Paragraphs>
      </itemcol>
      <itemcol>
        <word>FALTA</word>
        <filepath>\\192.168.2.2\00 - Departments\Common\scan\captain.3027\SOC Tours\2014\03.- MARZO\20 MAR 2014 Area de Residuos  22 00 .pdf</filepath>
        <Paragraphs>FALTA SEGREGACION ADECUADA  EXCESO DE RESIDUOS EN CONTENEDORES  E </Paragraphs>
      </itemcol>
      <itemcol>
        <word>FALTA</word>
        <filepath>\\192.168.2.2\00 - Departments\Common\scan\captain.3027\SOC Tours\2014\03.- MARZO\27 MAR 2014Ponton ETB  22 00.pdf</filepath>
        <Paragraphs>V  Safety Tour                           PONTON ESTRIBOR    22:00 HRS MARCH 27 2014 SE OBSERVA FALTA DE CULTURA EN MATERIA DE ORDEN Y LIM-</Paragraphs>
      </itemcol>
      <itemcol>
        <word>FALTA</word>
        <filepath>\\192.168.2.2\00 - Departments\Common\scan\captain.3027\SOC Tours\2014\03.- MARZO\29 MAR 2014 Drill floor   22 00.pdf</filepath>
        <Paragraphs>V  Safety Tour                           RIG FLOOR  22:00 HRS MARCH 292014 FALTA DE ORDEN EN EL CUARTO DE </Paragraphs>
      </itemcol>
      <itemcol>
        <word>FALTA</word>
        <filepath>\\192.168.2.2\00 - Departments\Common\scan\captain.3027\SOC Tours\2014\04.- ABRIL\01 ABRIL 2014 POPA  22 00.pdf</filepath>
        <Paragraphs>FALTA SEGUROS EN LAS CAJAS   </Paragraphs>
      </itemcol>
      <itemcol>
        <word>FALTA</word>
        <filepath>\\192.168.2.2\00 - Departments\Common\scan\captain.3027\SOC Tours\2014\04.- ABRIL\06 ABRIL 2014 ALL AREAS 10 00 HRS.pdf</filepath>
        <Paragraphs>DE LA ESCALERA DE ESCAPE FALTA SEGURO PLASTICO A EXTINTOR EN ES-</Paragraphs>
      </itemcol>
      <itemcol>
        <word>FALTA</word>
        <filepath>\\192.168.2.2\00 - Departments\Common\scan\captain.3027\SOC Tours\2014\04.- ABRIL\08 ABRIL 2014 DERRICK.pdf</filepath>
        <Paragraphs>FALTA COLOCAR SE361 ALAMIENTO  DE SEGURIDAD EN AC-</Paragraphs>
      </itemcol>
      <itemcol>
        <word>FALTA</word>
        <filepath>\\192.168.2.2\00 - Departments\Common\scan\captain.3027\SOC Tours\2014\04.- ABRIL\09 ABRIL 2014 CHIMNEYS.pdf</filepath>
        <Paragraphs>FALTA COLOCAR SE361ALAMIENTO  DE SEGURIDAD  EN </Paragraphs>
      </itemcol>
      <itemcol>
        <word>FALTA</word>
        <filepath>\\192.168.2.2\00 - Departments\Common\scan\captain.3027\SOC Tours\2014\04.- ABRIL\09 ABRIL 2014 DRILL FLOOR.pdf</filepath>
        <Paragraphs>FALTA ORDEN Y LIMPIEZA  </Paragraphs>
      </itemcol>
      <itemcol>
        <word>FALTA</word>
        <filepath>\\192.168.2.2\00 - Departments\Common\scan\captain.3027\SOC Tours\2014\04.- ABRIL\12 ABRIL 2014 Air Pressure Vessel Deck.pdf</filepath>
        <Paragraphs>FALTA DE ORDEN Y LIMPIEZA </Paragraphs>
      </itemcol>
      <itemcol>
        <word>FALTA</word>
        <filepath>\\192.168.2.2\00 - Departments\Common\scan\captain.3027\SOC Tours\2014\04.- ABRIL\12 ABRIL 2014 MUD TANK COLUMNA ESTRIBOR.pdf</filepath>
        <Paragraphs>FALTA LIMPIEZA EN AREA DE TANQUES DE LODOS.</Paragraphs>
      </itemcol>
      <itemcol>
        <word>FALTA</word>
        <filepath>\\192.168.2.2\00 - Departments\Common\scan\captain.3027\SOC Tours\2014\04.- ABRIL\13 ABRIL 2014 MOON POOL.pdf</filepath>
        <Paragraphs>V  Safety Tour                  MOON POOL,HIDR ROOM &amp; PUMP ROOM  10:00 HRS APRIL 13th 2014MOON POOL/227ACEITE  REGADO, FALTA ORDEN Y LIMPIEZA</Paragraphs>
      </itemcol>
      <itemcol>
        <word>FALTA</word>
        <filepath>\\192.168.2.2\00 - Departments\Common\scan\captain.3027\SOC Tours\2014\04.- ABRIL\14 STORE ROOM.pdf</filepath>
        <Paragraphs>FALTA COLOCAR SE361ALAMIENTO  DE PUERTA BLO-</Paragraphs>
      </itemcol>
      <itemcol>
        <word>FALTA</word>
        <filepath>\\192.168.2.2\00 - Departments\Common\scan\captain.3027\SOC Tours\2014\04.- ABRIL\17 Shaker room 2200 hrs .pdf</filepath>
        <Paragraphs>APRIL   th      FALTA DE ORDEN Y LIMPIEZA EN ENTRADA Y FRENTE  DE TEMBLORINAS  </Paragraphs>
      </itemcol>
      <itemcol>
        <word>FALTA</word>
        <filepath>\\192.168.2.2\00 - Departments\Common\scan\captain.3027\SOC Tours\2014\04.- ABRIL\17 Shaleshakers 1000 hrs .pdf</filepath>
        <Paragraphs>FALTA ORDEN Y LIMPIEZA </Paragraphs>
      </itemcol>
      <itemcol>
        <word>FALTA</word>
        <filepath>\\192.168.2.2\00 - Departments\Common\scan\captain.3027\SOC Tours\2014\04.- ABRIL\18 Upper Deck Ventilation Room.pdf</filepath>
        <Paragraphs>FALTA ORDEN Y LIMPIEZA </Paragraphs>
      </itemcol>
      <itemcol>
        <word>FALTA</word>
        <filepath>\\192.168.2.2\00 - Departments\Common\scan\captain.3027\SOC Tours\2014\04.- ABRIL\19 Cement unit.pdf</filepath>
        <Paragraphs>                        PSSP LA MURALLA IV  Safety Tour                  CEMENT UNIT 22:00 HRS APRIL 19th 2014 FALTA DE ORDEN Y LIMPIEZA </Paragraphs>
      </itemcol>
      <itemcol>
        <word>FALTA</word>
        <filepath>\\192.168.2.2\00 - Departments\Common\scan\captain.3027\SOC Tours\2014\04.- ABRIL\23 Upper Pipe Deck.pdf</filepath>
        <Paragraphs>WELD BURNS NO TOUCHED UP  FALTA ORDEN Y LIMPIEZA </Paragraphs>
      </itemcol>
      <itemcol>
        <word>FALTA</word>
        <filepath>\\192.168.2.2\00 - Departments\Common\scan\captain.3027\SOC Tours\2014\05.- MAYO\05 Taller de Herramientas de perforacion.pdf</filepath>
        <Paragraphs>FALTA ORDEN Y LIMPIEZA  </Paragraphs>
      </itemcol>
      <itemcol>
        <word>FALTA</word>
        <filepath>\\192.168.2.2\00 - Departments\Common\scan\captain.3027\SOC Tours\2014\05.- MAYO\07 Mud Mix Control Room.pdf</filepath>
        <Paragraphs>FALTA ORDEN Y LIMPIEZA EN GABINETES    </Paragraphs>
      </itemcol>
      <itemcol>
        <word>FALTA</word>
        <filepath>\\192.168.2.2\00 - Departments\Common\scan\captain.3027\SOC Tours\2014\05.- MAYO\10 Cement room .pdf</filepath>
        <Paragraphs>FALTA ORGANIZAR EQUIPO </Paragraphs>
      </itemcol>
      <itemcol>
        <word>FALTA</word>
        <filepath>\\192.168.2.2\00 - Departments\Common\scan\captain.3027\SOC Tours\2014\05.- MAYO\15  temblorinas 22 00.pdf</filepath>
        <Paragraphs>FALTA ORDEN Y LIMPIEZA</Paragraphs>
      </itemcol>
      <itemcol>
        <word>FALTA</word>
        <filepath>\\192.168.2.2\00 - Departments\Common\scan\captain.3027\SOC Tours\2014\05.- MAYO\15 MAYO 2014 DRILL FLOOR.pdf</filepath>
        <Paragraphs>FALTA IDENTIFICAR APROPIADAMENTE LA RUTA DE  </Paragraphs>
      </itemcol>
      <itemcol>
        <word>FALTA</word>
        <filepath>\\192.168.2.2\00 - Departments\Common\scan\captain.3027\SOC Tours\2014\05.- MAYO\16 MAYO 2014 MoonPool.pdf</filepath>
        <Paragraphs>V  Safety Tour                   MoonPool  10:00 HRS MAY 16th 2014 FALTA ORDEN Y LIMPIEZA</Paragraphs>
      </itemcol>
      <itemcol>
        <word>FALTA</word>
        <filepath>\\192.168.2.2\00 - Departments\Common\scan\captain.3027\SOC Tours\2014\05.- MAYO\20 MAYO 2014 presas.pdf</filepath>
        <Paragraphs>S MAY   th      FALTA RETRACTIL DEL TRIPODE DE RESCATEEQUIPOS Y MATERIALES DE LIMPIEZA MAL ALMACENADOS EN TODA EL AREA  </Paragraphs>
      </itemcol>
      <itemcol>
        <word>FALTA</word>
        <filepath>\\192.168.2.2\00 - Departments\Common\scan\captain.3027\SOC Tours\2014\05.- MAYO\23 MAYO 2014 Helipuerto .pdf</filepath>
        <Paragraphs>FALTA  FIJAR CONTENEDOR DE MUESTRAS DIARIAS DE </Paragraphs>
      </itemcol>
      <itemcol>
        <word>FALTA</word>
        <filepath>\\192.168.2.2\00 - Departments\Common\scan\captain.3027\SOC Tours\2014\05.- MAYO\24 MAYO 2014 Cuarto maquinas #4.pdf</filepath>
        <Paragraphs>FALTA SE321ALIZAR LAS RUTAS DE EVACUACION EN PAREDES Y PISOS FALTA SE321ALAMIENTO DE SUPERFICIES CALIENTES</Paragraphs>
      </itemcol>
      <itemcol>
        <word>FALTA</word>
        <filepath>\\192.168.2.2\00 - Departments\Common\scan\captain.3027\SOC Tours\2014\05.- MAYO\25 MAYO 2014  CUARTO DE BATERIAS Y UPS.pdf</filepath>
        <Paragraphs>FALTA SE321ALIZAR ENTRADAS A CUARTO DE UPS Y BATERIAS COMO AREAS CON RIESGOS ELECTRICOS</Paragraphs>
      </itemcol>
      <itemcol>
        <word>FALTA</word>
        <filepath>\\192.168.2.2\00 - Departments\Common\scan\captain.3027\SOC Tours\2014\05.- MAYO\27 MAYO 2014  HOSPITAL.pdf</filepath>
        <Paragraphs>FALTA IDENTIFICACION DEL CONTENEDOR   </Paragraphs>
      </itemcol>
      <itemcol>
        <word>FALTA</word>
        <filepath>\\192.168.2.2\00 - Departments\Common\scan\captain.3027\SOC Tours\2014\05.- MAYO\27 MAYO 2014  MCC ROOM M 105.pdf</filepath>
        <Paragraphs>FALTA PERMISO A LA VISTA EN EL AREA DEL TRABAJO  ORDEN Y LIMPIEZA ADECUADA  </Paragraphs>
      </itemcol>
      <itemcol>
        <word>FALTA</word>
        <filepath>\\192.168.2.2\00 - Departments\Common\scan\captain.3027\SOC Tours\2014\05.- MAYO\30 MAYO 2014  CEMENT ROOM.pdf</filepath>
        <Paragraphs>TARIMAS DE MATERIALES QUIMICOS, FALTA COLO-</Paragraphs>
      </itemcol>
      <itemcol>
        <word>FALTA</word>
        <filepath>\\192.168.2.2\00 - Departments\Common\scan\captain.3027\SOC Tours\2014\05.- MAYO\31 MAYO 2014  HIDRAULIC ROOM BOP.pdf</filepath>
        <Paragraphs>FALTA COLOCAR SENALAMIENTO DE SAIDA   </Paragraphs>
      </itemcol>
      <itemcol>
        <word>FALTA</word>
        <filepath>\\192.168.2.2\00 - Departments\Common\scan\captain.3027\SOC Tours\2014\06.- JUNIO\02 Junio Electric Motors Store.pdf</filepath>
        <Paragraphs>FALTA ORDEN Y LIMPIEZA  </Paragraphs>
      </itemcol>
      <itemcol>
        <word>FALTA</word>
        <filepath>\\192.168.2.2\00 - Departments\Common\scan\captain.3027\SOC Tours\2014\06.- JUNIO\03 JAN 2014 MUD PUMP ROOM.pdf</filepath>
        <Paragraphs>FALTA COLOCAR SENALAMIENTO DE SEGURIDAD EN </Paragraphs>
      </itemcol>
      <itemcol>
        <word>FALTA</word>
        <filepath>\\192.168.2.2\00 - Departments\Common\scan\captain.3027\SOC Tours\2014\06.- JUNIO\03 JUN 2014 MUD PUMP ROOM.pdf</filepath>
        <Paragraphs>FALTA COLOCAR SENALAMIENTO DE SEGURIDAD EN </Paragraphs>
      </itemcol>
      <itemcol>
        <word>FALTA</word>
        <filepath>\\192.168.2.2\00 - Departments\Common\scan\captain.3027\SOC Tours\2014\06.- JUNIO\05 JUN 2014  MAIN DECK.pdf</filepath>
        <Paragraphs>AUDITIVOS EN TALLER DE SOLDADURA FALTA CHAVETA DE SEGURIDAD EN GRILLETE DE  </Paragraphs>
      </itemcol>
      <itemcol>
        <word>FALTA</word>
        <filepath>\\192.168.2.2\00 - Departments\Common\scan\captain.3027\SOC Tours\2014\06.- JUNIO\10 Jun Aft Port Funnel.pdf</filepath>
        <Paragraphs>MUY MALA PRACTICA DE DESORDEN Y FALTA DE LIMPIEZA  </Paragraphs>
      </itemcol>
      <itemcol>
        <word>FALTA</word>
        <filepath>\\192.168.2.2\00 - Departments\Common\scan\captain.3027\SOC Tours\2014\06.- JUNIO\15 Jun Different Rig Areas.pdf</filepath>
        <Paragraphs>FALTA CHAVETA DE SEGURIDAD EN CONEXION </Paragraphs>
      </itemcol>
      <itemcol>
        <word>FALTA</word>
        <filepath>\\192.168.2.2\00 - Departments\Common\scan\captain.3027\SOC Tours\2014\06.- JUNIO\18 Shakers rooms.pdf</filepath>
        <Paragraphs>FALTA DE MICA EN LAS CAJAS DE MANGUERA Y ERA  </Paragraphs>
      </itemcol>
      <itemcol>
        <word>FALTA</word>
        <filepath>\\192.168.2.2\00 - Departments\Common\scan\captain.3027\SOC Tours\2014\06.- JUNIO\19 Compresores de refrigerante M202.pdf</filepath>
        <Paragraphs>FALTA DE ORDEN Y LIMPIEZA Y REACOMOPDO DE MATERIAL Y EQUIPO  </Paragraphs>
      </itemcol>
      <itemcol>
        <word>FALTA</word>
        <filepath>\\192.168.2.2\00 - Departments\Common\scan\captain.3027\SOC Tours\2014\06.- JUNIO\28 Jun Almacen de Oxigeno y Acetileno .pdf</filepath>
        <Paragraphs>GOOD HOUSEKEEPING  FALTA ORDEN Y LIMPIEZA </Paragraphs>
      </itemcol>
      <itemcol>
        <word>FALTA</word>
        <filepath>\\192.168.2.2\00 - Departments\Common\scan\captain.3027\SOC Tours\2014\10.- OCTUBRE\09 Cuerto de Ventilacion TW Deck .pdf</filepath>
        <Paragraphs>FALTA SEGREGACION DE RESIDUOS  </Paragraphs>
      </itemcol>
      <itemcol>
        <word>FALTA</word>
        <filepath>\\192.168.2.2\00 - Departments\Common\scan\captain.3027\SOC Tours\2014\10.- OCTUBRE\11 UTILITY ROOM M 106.pdf</filepath>
        <Paragraphs> M 106 10:00 HRS  OCT. 11Th, 2014 FALTA VIGIA EN LA ENTRADA </Paragraphs>
      </itemcol>
      <itemcol>
        <word>FALTA</word>
        <filepath>\\192.168.2.2\00 - Departments\Common\scan\captain.3027\SOC Tours\2014\10.- OCTUBRE\12 Cement room.pdf</filepath>
        <Paragraphs>EYE WASH NOZZLE CAPS OUT (CORRECTED)   FALTA DE ORDEN Y LIMPIEZA Y MANGUER</Paragraphs>
      </itemcol>
      <itemcol>
        <word>FALTA</word>
        <filepath>\\192.168.2.2\00 - Departments\Common\scan\captain.3027\SOC Tours\2014\11. NOVIEMBRE\27.- Upper pipe deck.pdf</filepath>
        <Paragraphs>22:00 HRS NOVEMBER 27th , 2014 FALTA DE ORDEN Y LIMPIEZA DENTRO</Paragraphs>
      </itemcol>
      <itemcol>
        <word>FALTA</word>
        <filepath>\\192.168.2.2\00 - Departments\Common\scan\captain.3027\SOC Tours\2014\11. NOVIEMBRE\28 WELDING SHOP.pdf</filepath>
        <Paragraphs>BER   th        FALTA SEGREGACION ADECUADA DE RESIDUOS     </Paragraphs>
      </itemcol>
      <itemcol>
        <word>FALTA</word>
        <filepath>\\192.168.2.2\00 - Departments\Common\scan\captain.3027\SOC Tours\2014\12. DICIEMBRE\01 SHAKER .pdf</filepath>
        <Paragraphs>SHAKER ROOM 10:00 HRS DECEMBER 01 ,2014 FALTA DE ORDEN Y LIMPIEZA / </Paragraphs>
      </itemcol>
      <itemcol>
        <word>FALTA</word>
        <filepath>\\192.168.2.2\00 - Departments\Common\scan\captain.3027\SOC Tours\2014\12. DICIEMBRE\01.- Drill floor Heavy tool store.pdf</filepath>
        <Paragraphs>FALTA DE ORDEN, MATERIAL SUELTO Y SIN ASEGURAR EN EL PISO </Paragraphs>
      </itemcol>
      <itemcol>
        <word>FALTA</word>
        <filepath>\\192.168.2.2\00 - Departments\Common\scan\captain.3027\SOC Tours\2014\12. DICIEMBRE\07.- WEEKLY SOC TOUR.pdf</filepath>
        <Paragraphs>FALTA ORDEN Y LIMPIEZA /</Paragraphs>
      </itemcol>
      <itemcol>
        <word>FALTA</word>
        <filepath>\\192.168.2.2\00 - Departments\Common\scan\captain.3027\SOC Tours\2014\12. DICIEMBRE\10 MAIN DECK STARBOARD SIDE   .pdf</filepath>
        <Paragraphs>FALTA ORDEN Y LIMPIEZA</Paragraphs>
      </itemcol>
      <itemcol>
        <word>FALTA</word>
        <filepath>\\192.168.2.2\00 - Departments\Common\scan\captain.3027\SOC Tours\2014\12. DICIEMBRE\11.- MWD AREA.pdf</filepath>
        <Paragraphs>FALTA CALCE DE  MADERA EN BASES  DE TOTHER222S  </Paragraphs>
      </itemcol>
      <itemcol>
        <word>FALTA</word>
        <filepath>\\192.168.2.2\00 - Departments\Common\scan\captain.3027\SOC Tours\2014\12. DICIEMBRE\15.- Welding Shop.pdf</filepath>
        <Paragraphs>22:00 HRS   DEC. 15th , 2014 FALTA ORDEN Y LIMPIEZA </Paragraphs>
      </itemcol>
      <itemcol>
        <word>FALTA</word>
        <filepath>\\192.168.2.2\00 - Departments\Common\scan\captain.3027\SOC Tours\2014\12. DICIEMBRE\17 Moon Pool.pdf</filepath>
        <Paragraphs>FALTA  ORDEN Y LIMPIEZA EN GENERAL </Paragraphs>
      </itemcol>
      <itemcol>
        <word>FALTA</word>
        <filepath>\\192.168.2.2\00 - Departments\Common\scan\captain.3027\SOC Tours\2014\12. DICIEMBRE\17 Sewage plant room.pdf</filepath>
        <Paragraphs> AISLE NOT FREE  FALTA DE ORDEN Y LIMPIEZA </Paragraphs>
      </itemcol>
      <itemcol>
        <word>FALTA</word>
        <filepath>\\192.168.2.2\00 - Departments\Common\scan\captain.3027\SOC Tours\2014\12. DICIEMBRE\18 EngineWorkShop M-120.pdf</filepath>
        <Paragraphs>FALTA ROMBO DE SEGURIDAD EN CONTENEDORES DE SUSTANCIAS  </Paragraphs>
      </itemcol>
      <itemcol>
        <word>FALTA</word>
        <filepath>\\192.168.2.2\00 - Departments\Common\scan\captain.3027\SOC Tours\2014\12. DICIEMBRE\20.-Machine shop .pdf</filepath>
        <Paragraphs>FALTA REMARCAR LOS NIVELES DE RIESGO  </Paragraphs>
      </itemcol>
      <itemcol>
        <word>FALTA</word>
        <filepath>\\192.168.2.2\00 - Departments\Common\scan\captain.3027\SOC Tours\2014\12. DICIEMBRE\21.- SHALE SHAKER .pdf</filepath>
        <Paragraphs>22:00 HRS  21 DECEMBER  FALTA DE ORDEN Y LIMPIEZA / </Paragraphs>
      </itemcol>
      <itemcol>
        <word>FALTA</word>
        <filepath>\\192.168.2.2\00 - Departments\Common\scan\captain.3027\SOC Tours\2014\12. DICIEMBRE\22.-DRILL FLOR .pdf</filepath>
        <Paragraphs>FALTA ORDEN Y LIMPIEZA </Paragraphs>
      </itemcol>
      <itemcol>
        <word>FALTA</word>
        <filepath>\\192.168.2.2\00 - Departments\Common\scan\captain.3027\SOC Tours\2014\12. DICIEMBRE\24 Hidraulic and Hp Compressor room .pdf</filepath>
        <Paragraphs>FALTA REMARCAR  NIVELES DE RIESGO EN </Paragraphs>
      </itemcol>
      <itemcol>
        <word>FALTA</word>
        <filepath>\\192.168.2.2\00 - Departments\Common\scan\captain.3027\SOC Tours\2014\12. DICIEMBRE\25 AFT Port SIde Pontoon .pdf</filepath>
        <Paragraphs>FALTA LIMPIEZA EN  CENTINAS </Paragraphs>
      </itemcol>
      <itemcol>
        <word>FALTA</word>
        <filepath>\\192.168.2.2\00 - Departments\Common\scan\captain.3027\SOC Tours\2014\12. DICIEMBRE\26.-Cement Room.pdf</filepath>
        <Paragraphs>FALTA TAPONES AUDITIVOS (CORREGIDO) </Paragraphs>
      </itemcol>
      <itemcol>
        <word>FALTA</word>
        <filepath>\\192.168.2.2\00 - Departments\Common\scan\captain.3027\SOC Tours\2014\12. DICIEMBRE\31.- CUBIERTA PROA2.pdf</filepath>
        <Paragraphs>FALTA SE321ALIZAR  </Paragraphs>
      </itemcol>
      <itemcol>
        <word>FALTA</word>
        <filepath>\\192.168.2.2\00 - Departments\Common\scan\captain.3027\SOC Tours\2014\12. DICIEMBRE\31.- sack room.pdf</filepath>
        <Paragraphs>FALTA ORDEN Y LIMPIEZA </Paragraphs>
      </itemcol>
      <itemcol>
        <word>FALTA</word>
        <filepath>\\192.168.2.2\00 - Departments\Common\scan\captain.3027\SOC Tours\2015\ENERO\02 Moonpool.pdf</filepath>
        <Paragraphs>FALTA DE ORDEN / </Paragraphs>
      </itemcol>
      <itemcol>
        <word>FALTA</word>
        <filepath>\\192.168.2.2\00 - Departments\Common\scan\captain.3027\SOC Tours\2015\ENERO\03 CEMENT ROOM.pdf</filepath>
        <Paragraphs>10:00 HRS  JANUARY 03 rd , 2014 FALTA ORDEN Y LIMPIEZA PARTE SUPERIOR DE </Paragraphs>
      </itemcol>
      <itemcol>
        <word>FALTA</word>
        <filepath>\\192.168.2.2\00 - Departments\Common\scan\captain.3027\SOC Tours\2015\ENERO\03 MAIN DECK FWD.pdf</filepath>
        <Paragraphs>FALTA TAPA A BOTONERA </Paragraphs>
      </itemcol>
      <itemcol>
        <word>FALTA</word>
        <filepath>\\192.168.2.2\00 - Departments\Common\scan\captain.3027\SOC Tours\2015\ENERO\04 heavy tool room.pdf</filepath>
        <Paragraphs>RY    rd        FALTA SEGREGACION DE TRAPOS SUCIOS  </Paragraphs>
      </itemcol>
      <itemcol>
        <word>FALTA</word>
        <filepath>\\192.168.2.2\00 - Departments\Common\scan\captain.3027\SOC Tours\2015\ENERO\05 fire station #1.pdf</filepath>
        <Paragraphs>PLACE FALTA RELLENAR LOS CILINDROS DE AIRE </Paragraphs>
      </itemcol>
      <itemcol>
        <word>FALTA</word>
        <filepath>\\192.168.2.2\00 - Departments\Common\scan\captain.3027\SOC Tours\2015\ENERO\06 main deck STBD.pdf</filepath>
        <Paragraphs>22:00 HRS JANUARY 6 st , 2015 FALTA ACORDONAMIENTO EN TRABAJOS DE </Paragraphs>
      </itemcol>
      <itemcol>
        <word>FALTA</word>
        <filepath>\\192.168.2.2\00 - Departments\Common\scan\chiefofficer.3027\00 -Pre Arranque\Informe Reparacion Grua Er LM4 - PEMEX.pdf</filepath>
        <Paragraphs>F355sica  DESEMPE321O  FALTA DE  (cumplimiento). APLICACI323N  DE  PROCEDIMIENTOS  DE Causa </Paragraphs>
      </itemcol>
      <itemcol>
        <word>FALTA</word>
        <filepath>\\192.168.2.2\00 - Departments\Common\SOC Cards\SOC Tours\09.-SEPTIEMBRE\02 Cement room .pdf</filepath>
        <Paragraphs>FALTA CA,MBIAR ETIQUETAS O  </Paragraphs>
      </itemcol>
      <itemcol>
        <word>FALTA</word>
        <filepath>\\192.168.2.2\00 - Departments\Common\SOC Cards\SOC Tours\09.-SEPTIEMBRE\06 well test area .pdf</filepath>
        <Paragraphs>FALTA DE CHAVETA DE SEGURIDAD EN MUCHAS CANASTILLAS Y RACK DE TANQUES DE TUR-</Paragraphs>
      </itemcol>
      <itemcol>
        <word>FALTA</word>
        <filepath>\\192.168.2.2\00 - Departments\Common\SOC Cards\SOC Tours\09.-SEPTIEMBRE\07 Trampas de Arena Area.pdf</filepath>
        <Paragraphs>ABANDONADAS  FALTA DE ORDEN Y LIMPIEZA EN DIVERSAS ZONAS DEL AREA E </Paragraphs>
      </itemcol>
      <itemcol>
        <word>FALTA</word>
        <filepath>\\192.168.2.2\00 - Departments\Common\SOC Cards\SOC Tours\09.-SEPTIEMBRE\08 PORT SIDE PONTOON 22 00.pdf</filepath>
        <Paragraphs>FALTA UN EQUIPO DE RESPI\RACION AUTONOMO  FALTA ILUMUNACION EN ESPACIO VACIO  SEGREGACION INADECUADA DE RESIDUOS  </Paragraphs>
      </itemcol>
      <itemcol>
        <word>FALTA</word>
        <filepath>\\192.168.2.2\00 - Departments\Common\SOC Cards\SOC Tours\09.-SEPTIEMBRE\08 STARBOARD PONTOON 10 00.pdf</filepath>
        <Paragraphs>FALTA INSTALAR SENALAMIENTOS DE SEGURI- </Paragraphs>
      </itemcol>
      <itemcol>
        <word>FALTA</word>
        <filepath>\\192.168.2.2\00 - Departments\Common\SOC Cards\SOC Tours\09.-SEPTIEMBRE\10 SACS ROOM 22 00.pdf</filepath>
        <Paragraphs>MENTE  FALTA SE321ALIZAR CAJA DE EPP </Paragraphs>
      </itemcol>
      <itemcol>
        <word>FALTA</word>
        <filepath>\\192.168.2.2\00 - Departments\Common\SOC Cards\SOC Tours\09.-SEPTIEMBRE\11 Mud pump room.pdf</filepath>
        <Paragraphs>FALTA LIMPIEZA DE ALGUNAS AREAS </Paragraphs>
      </itemcol>
      <itemcol>
        <word>FALTA</word>
        <filepath>\\192.168.2.2\00 - Departments\Common\SOC Cards\SOC Tours\09.-SEPTIEMBRE\12 Engine room .pdf</filepath>
        <Paragraphs>V  Safety Tour                                  ENGINE ROOM                     10:00 HRS   SEPTEMBER 12TH, 2014 FALTA ROMBO DE SEGURIDAD  EN BIDON </Paragraphs>
      </itemcol>
      <itemcol>
        <word>FALTA</word>
        <filepath>\\192.168.2.2\00 - Departments\Common\SOC Cards\SOC Tours\09.-SEPTIEMBRE\13 ALMACEN.pdf</filepath>
        <Paragraphs>FALTA PERILLA QUE REGULA EL CIERRE DE  </Paragraphs>
      </itemcol>
      <itemcol>
        <word>FALTA</word>
        <filepath>\\192.168.2.2\00 - Departments\Common\SOC Cards\SOC Tours\09.-SEPTIEMBRE\13 MOON POOL.pdf</filepath>
        <Paragraphs>LIGHT BURNED OUT GRILLETE DE CUATRO PARTES FALTA PIN DE  </Paragraphs>
      </itemcol>
      <itemcol>
        <word>FALTA</word>
        <filepath>\\192.168.2.2\00 - Departments\Common\SOC Cards\SOC Tours\09.-SEPTIEMBRE\14.- Proa Estribor.pdf</filepath>
        <Paragraphs>V  Safety Tour                                    PROA ESTRIBOR              2200 HRS SEPTIEMBRE 14th , 2014MALACATE FALTA SE321ALIZAR MANIBELAS  </Paragraphs>
      </itemcol>
      <itemcol>
        <word>FALTA</word>
        <filepath>\\192.168.2.2\00 - Departments\Common\SOC Cards\SOC Tours\09.-SEPTIEMBRE\15.- ALMACEN DE SACOS.pdf</filepath>
        <Paragraphs>FALTA LIMPIEZA EN AREA DE MEZCLADO DE  </Paragraphs>
      </itemcol>
      <itemcol>
        <word>FALTA</word>
        <filepath>\\192.168.2.2\00 - Departments\Common\SOC Cards\SOC Tours\09.-SEPTIEMBRE\15.- PROA BABOR.pdf</filepath>
        <Paragraphs>FALTA  FIJAR  CAMARAS DE FRAGMENTACION DE  </Paragraphs>
      </itemcol>
      <itemcol>
        <word>FALTA</word>
        <filepath>\\192.168.2.2\00 - Departments\Common\SOC Cards\SOC Tours\09.-SEPTIEMBRE\16.- ALMACEN DE SACOS.pdf</filepath>
        <Paragraphs>NEED TO MOVE OUT FULL SACK FALTA LIMPIEZA EN AREA DE MEZCLADO </Paragraphs>
      </itemcol>
      <itemcol>
        <word>FALTA</word>
        <filepath>\\192.168.2.2\00 - Departments\Common\SOC Cards\SOC Tours\09.-SEPTIEMBRE\17.- AREA DE RESIDUOS.pdf</filepath>
        <Paragraphs>22:00 HRS SEPTIEMBRE 17th , 2014 FALTA LIMPIEZA AL CONCLUIR LOS </Paragraphs>
      </itemcol>
      <itemcol>
        <word>FALTA</word>
        <filepath>\\192.168.2.2\00 - Departments\Common\SOC Cards\SOC Tours\09.-SEPTIEMBRE\18 TALLER MECANICO-TORNO.pdf</filepath>
        <Paragraphs>PTIEMBRE   th   FALTA ORDEN EN LA PARTE SU</Paragraphs>
      </itemcol>
      <itemcol>
        <word>FALTA</word>
        <filepath>\\192.168.2.2\00 - Departments\Common\SOC Cards\SOC Tours\09.-SEPTIEMBRE\19 Chimenea de Popa Estribor.pdf</filepath>
        <Paragraphs>FALTA PERILLA DE  CONTROL MANUAL DE </Paragraphs>
      </itemcol>
      <itemcol>
        <word>FALTA</word>
        <filepath>\\192.168.2.2\00 - Departments\Common\SOC Cards\SOC Tours\09.-SEPTIEMBRE\20 LOWER SHAKER ROOM.pdf</filepath>
        <Paragraphs>FALTA IDENTIFICAR EL TIPO DE GRASA EN </Paragraphs>
      </itemcol>
      <itemcol>
        <word>FALTA</word>
        <filepath>\\192.168.2.2\00 - Departments\Common\SOC Cards\SOC Tours\09.-SEPTIEMBRE\21 MOON POOL.pdf</filepath>
        <Paragraphs>PASILLOS PRINCIPALES LIBRES, FALTA LIMPIEZA EN PASILLO DE LADO PROA (PISO RESBALOSO) </Paragraphs>
      </itemcol>
      <itemcol>
        <word>FALTA</word>
        <filepath>\\192.168.2.2\00 - Departments\Common\SOC Cards\SOC Tours\09.-SEPTIEMBRE\22 CUARTO DE OXIGENO Y ACETILENO.pdf</filepath>
        <Paragraphs>FALTA COLOCAR CAPUCHONES PARA ALGUNOS CILINDROS  </Paragraphs>
      </itemcol>
      <itemcol>
        <word>FALTA</word>
        <filepath>\\192.168.2.2\00 - Departments\Common\SOC Cards\SOC Tours\09.-SEPTIEMBRE\25 CUARTO QUIMICO.pdf</filepath>
        <Paragraphs>FALTA MANERAL DEL SISTEMA DE AIRE</Paragraphs>
      </itemcol>
      <itemcol>
        <word>FALTA</word>
        <filepath>\\192.168.2.2\00 - Departments\Common\SOC Cards\SOC Tours\09.-SEPTIEMBRE\27 TRIP SAVER.pdf</filepath>
        <Paragraphs>10:00 HRS SEPTIEMBRE 27th , FALTA INSTALAR RODAP</Paragraphs>
      </itemcol>
      <itemcol>
        <word>FALTA</word>
        <filepath>\\192.168.2.2\00 - Departments\Common\SOC Cards\SOC Tours\09.-SEPTIEMBRE\28 SEWAGE TREATMENT ROOM .pdf</filepath>
        <Paragraphs>FALTA SEGREGACION </Paragraphs>
      </itemcol>
      <itemcol>
        <word>FALTA</word>
        <filepath>\\192.168.2.2\00 - Departments\Common\SOC Cards\SOC Tours\09.-SEPTIEMBRE\29 WELDING WORK SHOP.pdf</filepath>
        <Paragraphs>RE   th         FALTA REUBICACION DE CILINDROS DE NITROGENO</Paragraphs>
      </itemcol>
      <itemcol>
        <word>FALTA</word>
        <filepath>\\192.168.2.2\00 - Departments\Common\SOC Cards\SOC Tours\10.- OCTUBRE\03 FRESH WATER GENERATOR ROOM.pdf</filepath>
        <Paragraphs>GOOD HOUSEKEEPING  FALTA SE321ALAMIENTO DE</Paragraphs>
      </itemcol>
      <itemcol>
        <word>FALTA</word>
        <filepath>\\192.168.2.2\00 - Departments\Common\SOC Cards\SOC Tours\10.- OCTUBRE\05 ALL AREAS.pdf</filepath>
        <Paragraphs>2014 FALTA TORNILLERIA EN</Paragraphs>
      </itemcol>
      <itemcol>
        <word>FALTA</word>
        <filepath>\\192.168.2.2\00 - Departments\Common\SOC Cards\SOC Tours\10.- OCTUBRE\15 CUBIERTA PRINCIPAL LADO ESTRIBOR.pdf</filepath>
        <Paragraphs>FALTA ORDEN Y LIMPIEZA</Paragraphs>
      </itemcol>
      <itemcol>
        <word>FALTA</word>
        <filepath>\\192.168.2.2\00 - Departments\Common\SOC Cards\SOC Tours\10.- OCTUBRE\19 Refrigerator Plant Room M202 .pdf</filepath>
        <Paragraphs>FALTA ORDEN Y LIMPIEZA</Paragraphs>
      </itemcol>
      <itemcol>
        <word>FALTA</word>
        <filepath>\\192.168.2.2\00 - Departments\Common\SOC Cards\SOC Tours\10.- OCTUBRE\21 Chimney room Aft-Stbd .pdf</filepath>
        <Paragraphs>EAS POPA-ESTRIBOR 21st   10:00 HRS  FALTA DE ORDEN Y LIMPIEZA </Paragraphs>
      </itemcol>
      <itemcol>
        <word>FALTA</word>
        <filepath>\\192.168.2.2\00 - Departments\Common\SOC Cards\SOC Tours\10.- OCTUBRE\21 OXY-ACET ROOM.pdf</filepath>
        <Paragraphs>FALTA CAMBIAR LAMPARA FUNDIDA / </Paragraphs>
      </itemcol>
      <itemcol>
        <word>FALTA</word>
        <filepath>\\192.168.2.2\00 - Departments\Common\SOC Cards\SOC Tours\10.- OCTUBRE\24 Starboard Aft Vent Room.pdf</filepath>
        <Paragraphs>FALTA ORDEN Y LIMPIEZA</Paragraphs>
      </itemcol>
      <itemcol>
        <word>FALTA</word>
        <filepath>\\192.168.2.2\00 - Departments\Common\SOC Cards\SOC Tours\10.- OCTUBRE\28 Battery Room M704.pdf</filepath>
        <Paragraphs>FALTA RACK  PARA ALMACENAMIENTO DE BATERIAS </Paragraphs>
      </itemcol>
      <itemcol>
        <word>FALTA</word>
        <filepath>\\192.168.2.2\00 - Departments\Common\SOC Cards\SOC Tours\10.- OCTUBRE\28 Top of vent. room strbd..pdf</filepath>
        <Paragraphs>FASTENING EQUIP. SCATTERED   FALTA REACOMODO DE MATERIALES </Paragraphs>
      </itemcol>
      <itemcol>
        <word>FALTA</word>
        <filepath>\\192.168.2.2\00 - Departments\Common\SOC Cards\SOC Tours\10.- OCTUBRE\29 bahia de risers.pdf</filepath>
        <Paragraphs>  OCT    h      FALTA ACORODNAMIENTOS EN AREA DE RIESGOS FALTA SEGREGACION ADECUADA  FALTAN  CHAVETAS QUE NOS GARANTIZEN UNA  </Paragraphs>
      </itemcol>
      <itemcol>
        <word>FALTA</word>
        <filepath>\\192.168.2.2\00 - Departments\Common\SOC Cards\SOC Tours\10.- OCTUBRE\30 oil station stbr.pdf</filepath>
        <Paragraphs>GUNOS TOTER LES FALTA ROMBO DE SEGURIDAD PEDAZOS DE MADERA REGADOS SOBRE Y ENTRE LOS TOTER DE ACEITE PEDAZOS DE MADERA REGADOS SOBRE Y ENTRE LOS TOTER</Paragraphs>
      </itemcol>
      <itemcol>
        <word>FALTA</word>
        <filepath>\\192.168.2.2\00 - Departments\Common\SOC Cards\SOC Tours\10.- OCTUBRE\31.- Drilling Utility Room..pdf</filepath>
        <Paragraphs>10:00 HRS OCTOBER 31 th , 2014 FALTA ORDEN Y LIMPIEZA   </Paragraphs>
      </itemcol>
      <itemcol>
        <word>FALTA</word>
        <filepath>\\192.168.2.2\00 - Departments\Common\SOC Cards\SOC Tours\10.- OCTUBRE\31.- taller de soldadura.pdf</filepath>
        <Paragraphs>22:00 HRS OCTOBER 31th , 2014 FALTA ORDEN Y LIMPIEZA   </Paragraphs>
      </itemcol>
      <itemcol>
        <word>FALTA</word>
        <filepath>\\192.168.2.2\00 - Departments\Common\SOC Cards\SOC Tours\11.- NOVIEMBRE\01.- tunel cableado babor L-D.pdf</filepath>
        <Paragraphs>FALTA DE ORDEN Y LIMPIEZA AL TERMINO  </Paragraphs>
      </itemcol>
      <itemcol>
        <word>FALTA</word>
        <filepath>\\192.168.2.2\00 - Departments\Common\SOC Cards\SOC Tours\11.- NOVIEMBRE\13.-CUARTO DE BOMBAS.pdf</filepath>
        <Paragraphs>        10:00 HRS NOVEMBER 13 th , 2014 CUBETAS CON ACITES ( FALTA ORDEN Y LIMPIEZA ) </Paragraphs>
      </itemcol>
      <itemcol>
        <word>FALTA</word>
        <filepath>\\192.168.2.2\00 - Departments\Common\SOC Cards\SOC Tours\11.- NOVIEMBRE\13.-U. ROOM M228 TW-POPA STRB.pdf</filepath>
        <Paragraphs>V  Safety Tour          UTILITY ROOM M228 TW/ POPA ESTR 22:00 HRS NOVEMBER 13 th , 2014 FALTA DE ORDEN Y LIMPIEZA, AREA INSEGURA DEJAN PIEZA EN MALA  </Paragraphs>
      </itemcol>
      <itemcol>
        <word>FALTA</word>
        <filepath>\\192.168.2.2\00 - Departments\Common\SOC Cards\SOC Tours\11.- NOVIEMBRE\14.- Coffee shop.pdf</filepath>
        <Paragraphs>FALTA ORDEN Y LIMPIEZA DESPACHADOR DE AGUA DE SABOR (FUENTE) NO FUN-</Paragraphs>
      </itemcol>
      <itemcol>
        <word>FALTA</word>
        <filepath>\\192.168.2.2\00 - Departments\Common\SOC Cards\SOC Tours\11.- NOVIEMBRE\15.- ROV AREA.pdf</filepath>
        <Paragraphs>BARRICADED AREA AND GOOD HOUSEKEEPING FALTA ROMBO DE SEGURIDAD/ </Paragraphs>
      </itemcol>
      <itemcol>
        <word>FALTA</word>
        <filepath>\\192.168.2.2\00 - Departments\Common\SOC Cards\SOC Tours\11.- NOVIEMBRE\15.- UPPER PIPE DECK.pdf</filepath>
        <Paragraphs>10:00 HRS NOVEMBER 15 th , 2014 FALTA ORDEN Y LIMPIEZA </Paragraphs>
      </itemcol>
      <itemcol>
        <word>FALTA</word>
        <filepath>\\192.168.2.2\00 - Departments\Common\SOC Cards\SOC Tours\11.- NOVIEMBRE\16.-OBSERVATIONS OF THE WEEK.pdf</filepath>
        <Paragraphs>  FALTA ORDEN Y LIMPIEZA EN CUARTO DE BOMBAS  </Paragraphs>
      </itemcol>
      <itemcol>
        <word>FALTA</word>
        <filepath>\\192.168.2.2\00 - Departments\Common\SOC Cards\SOC Tours\11.- NOVIEMBRE\17 UPPER DECK DRILL TOOL STORE.pdf</filepath>
        <Paragraphs> FALTA ORDEN Y LIMPIEZA FALTA ORDEN Y LIMPIEZA  </Paragraphs>
      </itemcol>
      <itemcol>
        <word>FALTA</word>
        <filepath>\\192.168.2.2\00 - Departments\Common\SOC Cards\SOC Tours\11.- NOVIEMBRE\18.- nuevos talleres.pdf</filepath>
        <Paragraphs>ANDAMIO INSEGURIOLAMPARA SUELTA CON RIESGO DE CAER FALTA ORDEN Y LIMPIEZA AREA  CON AMBIENTE  ALTAMENTE </Paragraphs>
      </itemcol>
      <itemcol>
        <word>FALTA</word>
        <filepath>\\192.168.2.2\00 - Departments\Common\SOC Cards\SOC Tours\11.- NOVIEMBRE\18.- Stbd Fwd column.pdf</filepath>
        <Paragraphs>22:00 HRS NOVEMBER 18 th , 2014 ORDEN Y LIMPIEZA ADECUADA EN LA COLUMNA, SOLO FALTA LIMPIEZA EN VALVULA DE LA  </Paragraphs>
      </itemcol>
      <itemcol>
        <word>FALTA</word>
        <filepath>\\192.168.2.2\00 - Departments\Common\SOC Cards\SOC Tours\11.- NOVIEMBRE\19 MUD PIT ROOM.pdf</filepath>
        <Paragraphs>BARRICADED AREA  FALTA TAPON EN TOMA DE </Paragraphs>
      </itemcol>
      <itemcol>
        <word>FALTA</word>
        <filepath>\\192.168.2.2\00 - Departments\Common\SOC Cards\SOC Tours\11.- NOVIEMBRE\2.- CAFERERIA UP DECK D.pdf</filepath>
        <Paragraphs>FALTA DE MANTENIMIENTO A REFRIGERADOR  FUGA DE AGUA EN CAFETERA. </Paragraphs>
      </itemcol>
      <itemcol>
        <word>FALTA</word>
        <filepath>\\192.168.2.2\00 - Departments\Common\SOC Cards\SOC Tours\11.- NOVIEMBRE\21 CEMENT CONTROL ROOM.pdf</filepath>
        <Paragraphs>FALTA ORDEN Y LIMPIEZA CON SUSTANCIAS </Paragraphs>
      </itemcol>
      <itemcol>
        <word>FALTA</word>
        <filepath>\\192.168.2.2\00 - Departments\Common\SOC Cards\SOC Tours\11.- NOVIEMBRE\22 FOOD GRINDER AREA .pdf</filepath>
        <Paragraphs>FALTA INSTALAR SENALAMIENTO DE SEGURIDAD </Paragraphs>
      </itemcol>
      <itemcol>
        <word>FALTA</word>
        <filepath>\\192.168.2.2\00 - Departments\Common\SOC Cards\SOC Tours\11.- NOVIEMBRE\24.VOID SPACE 56P.pdf</filepath>
        <Paragraphs>FALTA ORDEN Y LIMPIEZA </Paragraphs>
      </itemcol>
      <itemcol>
        <word>FALTA</word>
        <filepath>\\192.168.2.2\00 - Departments\Common\SOC Cards\SOC Tours\11.- NOVIEMBRE\25.- DERRICK.pdf</filepath>
        <Paragraphs>FALTA ORDEN Y LIMPIEZA   </Paragraphs>
      </itemcol>
      <itemcol>
        <word>FALTA</word>
        <filepath>\\192.168.2.2\00 - Departments\Common\SOC Cards\SOC Tours\11.- NOVIEMBRE\3.- moon pool.pdf</filepath>
        <Paragraphs>V  Safety Tour            MOON POOL  22: 00 HRS NOVEMBER 3 rd , 2014 FALTA SE321ALIZACION QUE INDIQUE EL RIESGO DE  </Paragraphs>
      </itemcol>
      <itemcol>
        <word>FALTA</word>
        <filepath>\\192.168.2.2\00 - Departments\Common\SOC Cards\SOC Tours\11.- NOVIEMBRE\7.- DERRICK.pdf</filepath>
        <Paragraphs>FALTA ORDEN Y LIMPIEZA  CHAROLA ECOLOGICA CON REMANENTES DE  </Paragraphs>
      </itemcol>
      <itemcol>
        <word>FALTA</word>
        <filepath>\\192.168.2.2\00 - Departments\Common\SOC Cards\SOC Tours\11.- NOVIEMBRE\8.- CHIMENEAS.pdf</filepath>
        <Paragraphs>FALTA SENALAMIENTO DE SEGURIDAD EN TAN- </Paragraphs>
      </itemcol>
      <itemcol>
        <word>FALTA</word>
        <filepath>\\192.168.2.2\00 - Departments\Common\SOC Cards\SOC Tours\11.- NOVIEMBRE\8.-TEMBLORINAS.pdf</filepath>
        <Paragraphs>22: 00 HRS NOVEMBER 8th , 2014 FALTA  ORDEN Y LIMPIEZA  </Paragraphs>
      </itemcol>
      <itemcol>
        <word>FALTA</word>
        <filepath>\\192.168.2.2\00 - Departments\Common\SOC Cards\SOC Tours\11.- NOVIEMBRE\9.- TALLER DE SOLDADURA.pdf</filepath>
        <Paragraphs>CUENTA CON CADENA PLASTICA DISPONIBLE PERSONAL TOMA COMO PERCHERO VALVULA DE LAVA OJOS OBSTRUYENDO SU LIBRE ACCESO, SE OBSERVA FALTA DE </Paragraphs>
      </itemcol>
      <itemcol>
        <word>FALTA</word>
        <filepath>\\192.168.2.2\00 - Departments\Common\SOC Cards\SOC Tours\7.- July 2014\08 Moonpool.pdf</filepath>
        <Paragraphs>FALTA LIMPIEZA (PISOS SUCIOS Y TRAPOS) </Paragraphs>
      </itemcol>
      <itemcol>
        <word>FALTA</word>
        <filepath>\\192.168.2.2\00 - Departments\Common\SOC Cards\SOC Tours\7.- July 2014\10 JULY 2014 ROV..pdf</filepath>
        <Paragraphs>FALTA SENALIZAR  CON ROMBO DE SEGURIDAD EN </Paragraphs>
      </itemcol>
      <itemcol>
        <word>FALTA</word>
        <filepath>\\192.168.2.2\00 - Departments\Common\SOC Cards\SOC Tours\7.- July 2014\11 contenedor de ATP'S.pdf</filepath>
        <Paragraphs>SE OBSERVA FALTA DE LUMINARIAS DENTRO DEL CONTENEDOR.  </Paragraphs>
      </itemcol>
      <itemcol>
        <word>FALTA</word>
        <filepath>\\192.168.2.2\00 - Departments\Common\SOC Cards\SOC Tours\7.- July 2014\12 Pañol de pintura.pdf</filepath>
        <Paragraphs>MATERIALES MAL ALMACENADOS, CON RIESGO DE CAER AL PERSONAL, Y FALTA DE ORDEN Y LIMPIEZA.  </Paragraphs>
      </itemcol>
      <itemcol>
        <word>FALTA</word>
        <filepath>\\192.168.2.2\00 - Departments\Common\SOC Cards\SOC Tours\7.- July 2014\14 RIG FLOOR.pdf</filepath>
        <Paragraphs>MATERIALES Y HERRAMIENTAS DE MECANICOS MAL ALMACENADOS, FALTA DE ORDEN Y LIMPIEZA  </Paragraphs>
      </itemcol>
      <itemcol>
        <word>FALTA</word>
        <filepath>\\192.168.2.2\00 - Departments\Common\SOC Cards\SOC Tours\7.- July 2014\16 Area de Comisaria.pdf</filepath>
        <Paragraphs>FALTA DE EPP COMPLETO AL REALIZAR LA DESCARGA </Paragraphs>
      </itemcol>
      <itemcol>
        <word>FALTA</word>
        <filepath>\\192.168.2.2\00 - Departments\Common\SOC Cards\SOC Tours\7.- July 2014\18 Area del Ancla de linea de perf..pdf</filepath>
        <Paragraphs>FALTA DEAGUAR UNIDAD DE POTENCIA DE </Paragraphs>
      </itemcol>
      <itemcol>
        <word>FALTA</word>
        <filepath>\\192.168.2.2\00 - Departments\Common\SOC Cards\SOC Tours\7.- July 2014\19 JULY 2014 TORNO.pdf</filepath>
        <Paragraphs>FALTA ORDEN Y LIMPIEZA EN DIFERENTES AREAS DEL </Paragraphs>
      </itemcol>
      <itemcol>
        <word>FALTA</word>
        <filepath>\\192.168.2.2\00 - Departments\Common\SOC Cards\SOC Tours\7.- July 2014\20 Cuarto de maquinas 3.pdf</filepath>
        <Paragraphs>FALTA DE DELIMITACION  DE LAS RUTAS DE EVACUACION  </Paragraphs>
      </itemcol>
      <itemcol>
        <word>FALTA</word>
        <filepath>\\192.168.2.2\00 - Departments\Common\SOC Cards\SOC Tours\7.- July 2014\20 JULY 2014 UNIDAD DE ALTA.pdf</filepath>
        <Paragraphs>FALTA COLOCAR SE321ALAMIENTO DE SEGURIDAD EN  </Paragraphs>
      </itemcol>
      <itemcol>
        <word>FALTA</word>
        <filepath>\\192.168.2.2\00 - Departments\Common\SOC Cards\SOC Tours\7.- July 2014\22 Cto Htas de perf.pdf</filepath>
        <Paragraphs>V  Safety Tour                   CUARTO DE HTAS. PESADAS U/D   22:00 HRS JULY 23th  2014SE OBSERBA FALTA DE ACORDONAMIENTO Y FALTA </Paragraphs>
      </itemcol>
      <itemcol>
        <word>FALTA</word>
        <filepath>\\192.168.2.2\00 - Departments\Common\SOC Cards\SOC Tours\7.- July 2014\23 JULY 2014 LOWER SHAKER ROOM .pdf</filepath>
        <Paragraphs>  FALTA SEGREGACION DE RESIDUOS,  ORDEN Y LIMPIEZA EN PASILLO </Paragraphs>
      </itemcol>
      <itemcol>
        <word>FALTA</word>
        <filepath>\\192.168.2.2\00 - Departments\Common\SOC Cards\SOC Tours\7.- July 2014\23 JULY 2014 TALLER MECANICO.pdf</filepath>
        <Paragraphs>FALTA ALIMENTACION ELECTRICA DE 220 V EN EN-</Paragraphs>
      </itemcol>
      <itemcol>
        <word>FALTA</word>
        <filepath>\\192.168.2.2\00 - Departments\Common\SOC Cards\SOC Tours\7.- July 2014\24 Taller de soldadura.pdf</filepath>
        <Paragraphs>PODRIA RESBALAR Y LESIONAR A ALGUN TRABAJADOR FALTA ORDEN Y LIMPIEZA </Paragraphs>
      </itemcol>
      <itemcol>
        <word>FALTA</word>
        <filepath>\\192.168.2.2\00 - Departments\Common\SOC Cards\SOC Tours\7.- July 2014\26 JULY 2014 COLUMNA PROA STB.pdf</filepath>
        <Paragraphs>FALTA SEGREGAR RESIDUOS DE MANERA ADECUADA / </Paragraphs>
      </itemcol>
      <itemcol>
        <word>FALTA</word>
        <filepath>\\192.168.2.2\00 - Departments\Common\SOC Cards\SOC Tours\7.- July 2014\26 JULY 2014 PONTOON STB.pdf</filepath>
        <Paragraphs>JULY   th       FALTA EQUIPO DE AIRE  RESPIRABLE PARA EMERGEN </Paragraphs>
      </itemcol>
      <itemcol>
        <word>FALTA</word>
        <filepath>\\192.168.2.2\00 - Departments\Common\SOC Cards\SOC Tours\7.- July 2014\27 JULY 2014 MOON POOL.pdf</filepath>
        <Paragraphs>  FALTA ORDEN Y LIMPIEZA EN DIFERENTES AREAS DEL </Paragraphs>
      </itemcol>
      <itemcol>
        <word>FALTA</word>
        <filepath>\\192.168.2.2\00 - Departments\Common\SOC Cards\SOC Tours\7.- July 2014\28 JULY 2014 CUARTO DE BOMBAS.pdf</filepath>
        <Paragraphs> 22:00 HRS JULY 28th  2014 FALTA LIMPIEZA EN PASILLOS Y DETRAS DE CAJA DE HERRAMIENTAS / </Paragraphs>
      </itemcol>
      <itemcol>
        <word>FALTA</word>
        <filepath>\\192.168.2.2\00 - Departments\Common\SOC Cards\SOC Tours\7.- July 2014\29 Todas las Areas.pdf</filepath>
        <Paragraphs>FALTA DE SEGREGACION EN TEMBLORINAS</Paragraphs>
      </itemcol>
      <itemcol>
        <word>FALTA</word>
        <filepath>\\192.168.2.2\00 - Departments\Common\SOC Cards\SOC Tours\8.-Agosto 2014\01 OXY-ACET ROOM.pdf</filepath>
        <Paragraphs>FALTA LIMPIEZA EN EL AREA / </Paragraphs>
      </itemcol>
      <itemcol>
        <word>FALTA</word>
        <filepath>\\192.168.2.2\00 - Departments\Common\SOC Cards\SOC Tours\8.-Agosto 2014\05 HABITACIONAL CAFETERIA Y GYM.pdf</filepath>
        <Paragraphs>FALTA ASEGURAMIENTO DE ENFRIADOR DE  </Paragraphs>
      </itemcol>
      <itemcol>
        <word>FALTA</word>
        <filepath>\\192.168.2.2\00 - Departments\Common\SOC Cards\SOC Tours\8.-Agosto 2014\07 CUARTO DE HERRAMIENTAS PESADAS (HEAVY TOOLS ROOM).pdf</filepath>
        <Paragraphs>TO    th        FALTA LETREROS DE SEGURIDAD EN LA </Paragraphs>
      </itemcol>
      <itemcol>
        <word>FALTA</word>
        <filepath>\\192.168.2.2\00 - Departments\Common\SOC Cards\SOC Tours\8.-Agosto 2014\21 MudPits.pdf</filepath>
        <Paragraphs>FALTA LIMPIEZA </Paragraphs>
      </itemcol>
      <itemcol>
        <word>FALTA</word>
        <filepath>\\192.168.2.2\00 - Departments\Common\SOC Cards\SOC Tours\8.-Agosto 2014\30 MAIN DECK.pdf</filepath>
        <Paragraphs>V  Safety Tour                     MAIN DECK  22:00 HRS             AUGUST 30th , 2014CONTENEDOR DE CHATARA FALTA LETRERO DE </Paragraphs>
      </itemcol>
      <itemcol>
        <word>FALTA</word>
        <filepath>\\192.168.2.2\00 - Departments\Common\SOC Cards\SOC Tours\8.-Agosto 2014\31 OXY-ACET ROOM.pdf</filepath>
        <Paragraphs>CYLINDERS NOT BEING USED WITHOUT CAPS OR MISPLACED CAPS FALTA CAMBIAR LAMPARA FUNDIDA / </Paragraphs>
      </itemcol>
      <itemcol>
        <word>FALTA</word>
        <filepath>\\192.168.2.2\00 - Departments\Common\TRA - Task Risk Assessment\Marine\TRA LAVADO CON ALTA PRECION.docx</filepath>
        <Paragraphs>S AL EQUIPO POR FALTA DE ACEITE O GRASA DA OS A PERSONAL POR LA ALTA PRECION    M    M    L    NO LAVAR SOBRE CAJAS ELECTRICAS  BOMBAS  PANELES  LAMPA</Paragraphs>
      </itemcol>
    </collection>
  </value>
  <key>FALTAN</key>
  <value>
    <collection>
      <itemcol>
        <word>FALTAN</word>
        <filepath>\\192.168.2.2\00 - Departments\Common\scan\captain.3027\SOC Tours\08.- AGOSTO\15 PORT SIDE PONTOON.pdf</filepath>
        <Paragraphs>FALTAN ERA  </Paragraphs>
      </itemcol>
      <itemcol>
        <word>FALTAN</word>
        <filepath>\\192.168.2.2\00 - Departments\Common\scan\captain.3027\SOC Tours\08.- AGOSTO\17 All AEREAS.pdf</filepath>
        <Paragraphs>FALTAN TAPONES PARA EL EQUIPO DE CASCADA </Paragraphs>
      </itemcol>
      <itemcol>
        <word>FALTAN</word>
        <filepath>\\192.168.2.2\00 - Departments\Common\scan\captain.3027\SOC Tours\08.- AGOSTO\18 INCINERATOR ROOM.pdf</filepath>
        <Paragraphs>FALTAN INSTRUCCIONES EN ESPA321OL </Paragraphs>
      </itemcol>
      <itemcol>
        <word>FALTAN</word>
        <filepath>\\192.168.2.2\00 - Departments\Common\scan\captain.3027\SOC Tours\2014\01.- ENERO\26 ENE 2013 SUB SEA.pdf</filepath>
        <Paragraphs>CONTENIDO       FALTAN AROS SALVAVIDAS E </Paragraphs>
      </itemcol>
      <itemcol>
        <word>FALTAN</word>
        <filepath>\\192.168.2.2\00 - Departments\Common\scan\captain.3027\SOC Tours\2014\01.- ENERO\31 ENE 2014 CTO. BOMBAS.pdf</filepath>
        <Paragraphs>FALTAN TAPONES AUDITIVOS FALTA DE LIMPIEZA, Y REPARACION DE </Paragraphs>
      </itemcol>
      <itemcol>
        <word>FALTAN</word>
        <filepath>\\192.168.2.2\00 - Departments\Common\scan\captain.3027\SOC Tours\2014\02.- FEBRERO\02 FEB 2014  INCINERADOR.pdf</filepath>
        <Paragraphs>V  SOC CARD TOUR            CUARTO DE INCINERADOR      02 DE FEBRERO DEL 2014 FALTAN PLACAS DE DOBLE FONDO SE RETIRARON Y NO LAS HAN PUESTO   </Paragraphs>
      </itemcol>
      <itemcol>
        <word>FALTAN</word>
        <filepath>\\192.168.2.2\00 - Departments\Common\scan\captain.3027\SOC Tours\2014\02.- FEBRERO\04 FEB 2014   .pdf</filepath>
        <Paragraphs>CONDICIONES, FALTAN MONJAS.</Paragraphs>
      </itemcol>
      <itemcol>
        <word>FALTAN</word>
        <filepath>\\192.168.2.2\00 - Departments\Common\scan\captain.3027\SOC Tours\2014\02.- FEBRERO\16 FEB 2014 1000.pdf</filepath>
        <Paragraphs>V  Safety Tour                   10:00 HRS 16  DE FEBRERO DE 2014 FALTAN SEGUROS DEL GANCHO</Paragraphs>
      </itemcol>
      <itemcol>
        <word>FALTAN</word>
        <filepath>\\192.168.2.2\00 - Departments\Common\SOC Cards\SOC Tours\09.-SEPTIEMBRE\29 INCINERATOR ROOM.pdf</filepath>
        <Paragraphs>READY FOR USE   FALTAN  INSTRUCCIONES EN </Paragraphs>
      </itemcol>
      <itemcol>
        <word>FALTAN</word>
        <filepath>\\192.168.2.2\00 - Departments\Common\SOC Cards\SOC Tours\09.-SEPTIEMBRE\29 WELDING WORK SHOP.pdf</filepath>
        <Paragraphs>FALTAN  VALVULAS CHECK   MULTICONTACTO INADECUADO PARA TRABAJOS </Paragraphs>
      </itemcol>
      <itemcol>
        <word>FALTAN</word>
        <filepath>\\192.168.2.2\00 - Departments\Common\SOC Cards\SOC Tours\09.-SEPTIEMBRE\30 HURRICAN GENERATOR ROOM.pdf</filepath>
        <Paragraphs>PERO FALTAN INSTRUCCIONES EN ESPA321OL/ </Paragraphs>
      </itemcol>
      <itemcol>
        <word>FALTAN</word>
        <filepath>\\192.168.2.2\00 - Departments\Common\SOC Cards\SOC Tours\10.- OCTUBRE\29 bahia de risers.pdf</filepath>
        <Paragraphs>ACION ADECUADA  FALTAN  CHAVETAS QUE NOS GARANTIZEN UNA  </Paragraphs>
      </itemcol>
      <itemcol>
        <word>FALTAN</word>
        <filepath>\\192.168.2.2\00 - Departments\Common\SOC Cards\SOC Tours\7.- July 2014\03 Gym and sauna.pdf</filepath>
        <Paragraphs>FALTAN PIEDRAS EN EL SAUNA </Paragraphs>
      </itemcol>
      <itemcol>
        <word>FALTAN</word>
        <filepath>\\192.168.2.2\00 - Departments\Common\SOC Cards\SOC Tours\7.- July 2014\09 new workshop.pdf</filepath>
        <Paragraphs>FALTAN CABLES DE PROTECCION PERIMETRAL EN ANDAMIOS AREA SIN BARRICADAS AL TERMINO DE ACTIVIDADES   </Paragraphs>
      </itemcol>
    </collection>
  </value>
  <key>FALL</key>
  <value>
    <collection>
      <itemcol>
        <word>FALL</word>
        <filepath>\\192.168.2.2\00 - Departments\Common\scan\captain.3027\SOC Tours\2014\02.- FEBRERO\10 FEB 2014 1000.pdf</filepath>
        <Paragraphs>TO PUT GUARDRAILS FALL PERSONAL CON EQUIPO ARRESTA CAIDAS/  </Paragraphs>
      </itemcol>
      <itemcol>
        <word>FALL</word>
        <filepath>\\192.168.2.2\00 - Departments\Common\scan\captain.3027\SOC Tours\2014\02.- FEBRERO\15 FEB 2014 1000 .pdf</filepath>
        <Paragraphs>FALL POINTS FALTA ORDEN Y LIMPIEZA</Paragraphs>
      </itemcol>
      <itemcol>
        <word>FALL</word>
        <filepath>\\192.168.2.2\00 - Departments\Common\scan\captain.3027\SOC Tours\2014\02.- FEBRERO\21 FEB 2014 1000.pdf</filepath>
        <Paragraphs>IDENTIFICATION PLATE ABOUT TO FALL OFF LA BASE DE CANASTILLA DE PERSONAL NO ESTA CER-</Paragraphs>
      </itemcol>
      <itemcol>
        <word>FALL</word>
        <filepath>\\192.168.2.2\00 - Departments\Common\scan\captain.3027\SOC Tours\2014\03.- MARZO\13 MAR 2014 1000.pdf</filepath>
        <Paragraphs>TO FALL</Paragraphs>
      </itemcol>
      <itemcol>
        <word>FALL</word>
        <filepath>\\192.168.2.2\00 - Departments\Common\scan\chiefofficer.3027\TRA 01\FORMATO VIEJO\TRA DE ALTURA NEW.docx</filepath>
        <Paragraphs>AR  LESIONES    FALL IN TO THE SEA  INJURIES    CANASTILLA EN MALAS CONDICIONES  BALZO INSEGURO Y CON DA OS  MAL ARMADO DE ANDAMIO DA OS A EXTREMIDADE</Paragraphs>
      </itemcol>
      <itemcol>
        <word>FALL</word>
        <filepath>\\192.168.2.2\00 - Departments\Common\scan\RSTC.3027\Catalog\9700505 Rev C 2014 DBI_SALA Catalog .pdf</filepath>
        <Paragraphs>THE ULTIMATE IN FALL PROTECTION   FULL LINE CATALOG            U N I T E D   S T A T E S  For more than    years  we have earned the trust of    compa</Paragraphs>
      </itemcol>
      <itemcol>
        <word>FALL</word>
        <filepath>\\192.168.2.2\00 - Departments\Common\scan\RSTC.3027\Catalog\9700506 Protecta Catalog USA Rev D_English.pdf</filepath>
        <Paragraphs>  UNITED STATES TRUSTED, QUALITY FALL PROTECTION   FULL LINE CATALOG   2015   COMPLIANCE PEOPLE AROUND </Paragraphs>
      </itemcol>
      <itemcol>
        <word>FALL</word>
        <filepath>\\192.168.2.2\00 - Departments\Common\scan\RSTC.3027\Catalog\DBI-SALA-AN.pdf</filepath>
        <Paragraphs>GLOBAL LEADER IN FALL PROTECTION    FULL LINE CATALOG </Paragraphs>
      </itemcol>
      <itemcol>
        <word>FALL</word>
        <filepath>\\192.168.2.2\00 - Departments\Common\scan\RSTC.3027\Catalog\MSA-Catalogue.pdf</filepath>
        <Paragraphs>faceen-USCALCULATING TOTAL FALL DISTANCE 036 ANCHOR POINT ABOVE USERen-USTOTAL FALL CLEARANCE REQUIRED = 2.5en-US</Paragraphs>
      </itemcol>
      <itemcol>
        <word>FALL</word>
        <filepath>\\192.168.2.2\00 - Departments\Common\scan\RSTC.3027\Catalog\slika~Honeywell Catalog 2013 2014.pdf</filepath>
        <Paragraphs>321Safety at Height FALL CLEARANCEGround and </Paragraphs>
      </itemcol>
      <itemcol>
        <word>FALL</word>
        <filepath>\\192.168.2.2\00 - Departments\Common\scan\Senior.Subsea\burner boom\user manual.pdf</filepath>
        <Paragraphs>EE FALL WHEN MAINTENANCE.  </Paragraphs>
      </itemcol>
      <itemcol>
        <word>FALL</word>
        <filepath>\\192.168.2.2\00 - Departments\Common\scan\Senior.Subsea\Procedures\077.PB021 - Retrieving the BOP Stack Assembly, Riser &amp; Diverter R.01 (16-Aug-13).docx</filepath>
        <Paragraphs>R RUN      FULL FALL PROTECTION MUST BE USED WHEN REMOVING MASTER BUSHINGS      HAVE PROPER FOOT PLACEMENT WHEN REMOVING BUSHINGS      HAVE A HOLE COV</Paragraphs>
      </itemcol>
      <itemcol>
        <word>FALL</word>
        <filepath>\\192.168.2.2\00 - Departments\Common\Share\313131\ELEVATORS&amp;SLIPS MANUALS\1 Material Request\Ribamar\NB11 Hull 3610\POs\PO-0001 Grant Prideco Drill String S-135\ODR-NB11-POR-0001.docx</filepath>
        <Paragraphs>RIDECO PRODUCTS FALL UNDER THE FOLLOWING    CATEGORIES     For Drill Pipe and HWDP ONLY    ECCN NO   EAR       HTS NO                  SCHEDULE B NO  </Paragraphs>
      </itemcol>
      <itemcol>
        <word>FALL</word>
        <filepath>\\192.168.2.2\00 - Departments\Common\Share\313131\ELEVATORS&amp;SLIPS MANUALS\1 Material Request\Ribamar\NB11 Hull 3610\POs\PO-0002 Grant Prideco Drill String\ODR-NB11-POR-0002.docx</filepath>
        <Paragraphs>RIDECO PRODUCTS FALL UNDER THE FOLLOWING CATEGORIES     For Drill Pipe and HWDP ONLY    ECCN NO   EAR       HTS NO                  SCHEDULE B NO     </Paragraphs>
      </itemcol>
      <itemcol>
        <word>FALL</word>
        <filepath>\\192.168.2.2\00 - Departments\Common\Share\313131\ELEVATORS&amp;SLIPS MANUALS\1 Material Request\Ribamar\NB11 Hull 3610\POs\PO-0003 Grant Prideco Drill String\ODR-NB11-POR-0003.docx</filepath>
        <Paragraphs>RIDECO PRODUCTS FALL UNDER THE FOLLOWING    CATEGORIES     For Drill Pipe and HWDP ONLY    ECCN NO   EAR       HTS NO                  SCHEDULE B NO  </Paragraphs>
      </itemcol>
      <itemcol>
        <word>FALL</word>
        <filepath>\\192.168.2.2\00 - Departments\Common\Share\313131\ELEVATORS&amp;SLIPS MANUALS\1 Material Request\Ribamar\NB11 Hull 3610\POs\PO-0005 Grant Prideco DS Componnents\Order Confirmation ODR-NB11-POR-0005.pdf</filepath>
        <Paragraphs>ALL NOV GRANT PRIDECO PRODUCTS FALL UNDER THE FOLLOWING  </Paragraphs>
      </itemcol>
      <itemcol>
        <word>FALL</word>
        <filepath>\\192.168.2.2\00 - Departments\Common\SOC Cards\SOC Tours\10.- OCTUBRE\21 OXY-ACET ROOM.pdf</filepath>
        <Paragraphs>UNFASTEN CYKINDER CAN FALL FRON </Paragraphs>
      </itemcol>
      <itemcol>
        <word>FALL</word>
        <filepath>\\192.168.2.2\00 - Departments\Common\SOC Cards\SOC Tours\7.- July 2014\07 Utility drilling room M159.pdf</filepath>
        <Paragraphs>BASURA QUE REQUIERE SER RETIRADA EQUIPMENT NOT SECURED, MAY FALL AND HURT SOMEBODY OR DAMGE</Paragraphs>
      </itemcol>
      <itemcol>
        <word>FALL</word>
        <filepath>\\192.168.2.2\00 - Departments\Common\SOC Cards\SOC Tours\8.-Agosto 2014\30 MAIN DECK.pdf</filepath>
        <Paragraphs>TOOLS THAT CAN FALL WITH RIG SHIFTING  </Paragraphs>
      </itemcol>
    </collection>
  </value>
  <key>FALLEN</key>
  <value>
    <collection>
      <itemcol>
        <word>FALLEN</word>
        <filepath>\\192.168.2.2\00 - Departments\Common\scan\captain.3027\SOC Tours\2014\02.- FEBRERO\10 FEB 2014 1000.pdf</filepath>
        <Paragraphs>PLATE TO PREVENT FAILURE FALLEN E </Paragraphs>
      </itemcol>
      <itemcol>
        <word>FALLEN</word>
        <filepath>\\192.168.2.2\00 - Departments\Common\scan\captain.3027\SOC Tours\2014\12. DICIEMBRE\22 Engine room #3.pdf</filepath>
        <Paragraphs> FALLEN SIGN(CORRECTED)  LETRERO SIN USO TIRADO(CORRECTED) </Paragraphs>
      </itemcol>
    </collection>
  </value>
  <key>FALLAS</key>
  <value>
    <collection>
      <itemcol>
        <word>FALLAS</word>
        <filepath>\\192.168.2.2\00 - Departments\Common\scan\captain.3027\SOC Tours\2014\02.- FEBRERO\15 FEB 2014 1000 .pdf</filepath>
        <Paragraphs>10:00 HRS 15 DE FEBRERO DE 2014  LAVA OJOS  DESHABILITADO POR FALLAS EN VALVULA</Paragraphs>
      </itemcol>
      <itemcol>
        <word>FALLAS</word>
        <filepath>\\192.168.2.2\00 - Departments\Common\scan\chiefofficer.3027\Well Info- Exploratus 1DL (North)\Programa de Perforación Exploratus -1DL_02-01-2015.pdf</filepath>
        <Paragraphs>                FALLAS GEOL GICAS                                                                                                                     </Paragraphs>
      </itemcol>
    </collection>
  </value>
  <key>TEMBLORINASFALTA</key>
  <value>
    <collection>
      <itemcol>
        <word>TEMBLORINASFALTA</word>
        <filepath>\\192.168.2.2\00 - Departments\Common\scan\captain.3027\SOC Tours\2014\04.- ABRIL\06 ABRIL 2014 ALL AREAS 10 00 HRS.pdf</filepath>
        <Paragraphs>DE COLAPSAR EN TEMBLORINASFALTA UN SOCKET A PRUEBA DE EXPLOCION EN ES- </Paragraphs>
      </itemcol>
    </collection>
  </value>
  <key>FALTANDO</key>
  <value>
    <collection>
      <itemcol>
        <word>FALTANDO</word>
        <filepath>\\192.168.2.2\00 - Departments\Common\scan\captain.3027\SOC Tours\2014\04.- ABRIL\11 ABRIL 2014 POPA BABOR L-D.pdf</filepath>
        <Paragraphs>CORRECTO ORDEN Y LIMPIEZA Y CONTINUA FALTANDO  </Paragraphs>
      </itemcol>
    </collection>
  </value>
  <key>2014FALTA</key>
  <value>
    <collection>
      <itemcol>
        <word>2014FALTA</word>
        <filepath>\\192.168.2.2\00 - Departments\Common\scan\captain.3027\SOC Tours\2014\04.- ABRIL\13 ABRIL 2014 DRAWWORKS.pdf</filepath>
        <Paragraphs>V  Safety Tour                  DRAWWORKS 22:00 HRS APRIL 13th 2014FALTA ORDEN Y LIMPIEZA </Paragraphs>
      </itemcol>
      <itemcol>
        <word>2014FALTA</word>
        <filepath>\\192.168.2.2\00 - Departments\Common\scan\captain.3027\SOC Tours\2014\05.- MAYO\12 Riser bay .pdf</filepath>
        <Paragraphs>V  Safety Tour                   RISER BAY 10:00 HRS MAY 12th 2014FALTA DE CINTA BARRICADA (CORREGIDA) </Paragraphs>
      </itemcol>
      <itemcol>
        <word>2014FALTA</word>
        <filepath>\\192.168.2.2\00 - Departments\Common\scan\captain.3027\SOC Tours\2014\05.- MAYO\15  temblorinas 22 00.pdf</filepath>
        <Paragraphs>V  Safety Tour                   Temblorinas   22:00 HRS MAY 15th 2014FALTA ORDEN Y LIMPIEZA  </Paragraphs>
      </itemcol>
      <itemcol>
        <word>2014FALTA</word>
        <filepath>\\192.168.2.2\00 - Departments\Common\scan\captain.3027\SOC Tours\2014\05.- MAYO\15 MAYO 2014 DRILL FLOOR.pdf</filepath>
        <Paragraphs>V  Safety Tour                   DRILL FLOOR  10:00 HRS MAY 15th 2014FALTA CAJA MET301LICA PARA COLOCAR COLLARINES</Paragraphs>
      </itemcol>
      <itemcol>
        <word>2014FALTA</word>
        <filepath>\\192.168.2.2\00 - Departments\Common\scan\captain.3027\SOC Tours\2014\05.- MAYO\23 MAYO 2014 Helipuerto .pdf</filepath>
        <Paragraphs>V  Safety Tour                   Helipuerto  22:00 HRS MAY 23th 2014FALTA DE ORDEN Y LIMPIEZA EN CASETA DE CONTRA </Paragraphs>
      </itemcol>
      <itemcol>
        <word>2014FALTA</word>
        <filepath>\\192.168.2.2\00 - Departments\Common\scan\captain.3027\SOC Tours\2014\06.- JUNIO\03 JAN 2014 MUD PUMP ROOM.pdf</filepath>
        <Paragraphs>V  Safety Tour                   MUD PUMP ROOM         10:00 HRS JAN 03 rd 2014FALTA LIMPIEZA DE ACEITE DERRAMADO SOBRE </Paragraphs>
      </itemcol>
      <itemcol>
        <word>2014FALTA</word>
        <filepath>\\192.168.2.2\00 - Departments\Common\scan\captain.3027\SOC Tours\2014\06.- JUNIO\03 JUN 2014 MUD PUMP ROOM.pdf</filepath>
        <Paragraphs>V  Safety Tour                   MUD PUMP ROOM         10:00 HRS JAN 03 rd 2014FALTA LIMPIEZA DE ACEITE DERRAMADO SOBRE </Paragraphs>
      </itemcol>
      <itemcol>
        <word>2014FALTA</word>
        <filepath>\\192.168.2.2\00 - Departments\Common\scan\captain.3027\SOC Tours\2014\12. DICIEMBRE\18 EngineWorkShop M-120.pdf</filepath>
        <Paragraphs>Taller Local de Maquinas        DEC 18TH    22:00 HRS , 2014FALTA ORGANIZACION, ORDEN Y LIMPIEZA </Paragraphs>
      </itemcol>
      <itemcol>
        <word>2014FALTA</word>
        <filepath>\\192.168.2.2\00 - Departments\Common\scan\captain.3027\SOC Tours\2014\12. DICIEMBRE\25 AFT Port SIde Pontoon .pdf</filepath>
        <Paragraphs>V  Safety Tour            AFT PORT SIDE  PONTOON DEC 25th22:00 HRS , 2014FALTA ORDEN Y LIMPIEZA EN CUARTO DE PROPULSOR #3 </Paragraphs>
      </itemcol>
      <itemcol>
        <word>2014FALTA</word>
        <filepath>\\192.168.2.2\00 - Departments\Common\SOC Cards\SOC Tours\09.-SEPTIEMBRE\02 Cement room .pdf</filepath>
        <Paragraphs>V  Safety Tour                   CEMENT UNIT              22:00 HRS          SEPTEMBER   02nd, 2014FALTA CAMBIAR LAMPARAS FUNDIDAS </Paragraphs>
      </itemcol>
      <itemcol>
        <word>2014FALTA</word>
        <filepath>\\192.168.2.2\00 - Departments\Common\SOC Cards\SOC Tours\09.-SEPTIEMBRE\12 unidad de alta presion.pdf</filepath>
        <Paragraphs>SEPTEMBER   TH      FALTA ORDEN Y LIMPIEZA EN TODO EL CUARTO DE  CEMENTACION Y ESTABLECER UN AREA ESPECIFICA </Paragraphs>
      </itemcol>
      <itemcol>
        <word>2014FALTA</word>
        <filepath>\\192.168.2.2\00 - Departments\Common\SOC Cards\SOC Tours\09.-SEPTIEMBRE\13 MOON POOL.pdf</filepath>
        <Paragraphs>V  Safety Tour                                    MOON POOL                  10:00 HRS SEPTIEMBRE 13th , 2014FALTA ROMBO DE SEGURIDAD  EN BIDON </Paragraphs>
      </itemcol>
      <itemcol>
        <word>2014FALTA</word>
        <filepath>\\192.168.2.2\00 - Departments\Common\SOC Cards\SOC Tours\09.-SEPTIEMBRE\15.- ALMACEN DE SACOS.pdf</filepath>
        <Paragraphs>10:00 HRS SEPTIEMBRE 15th , 2014FALTA INSTALAR SENALAMIENTO DE SALIDA DE  </Paragraphs>
      </itemcol>
      <itemcol>
        <word>2014FALTA</word>
        <filepath>\\192.168.2.2\00 - Departments\Common\SOC Cards\SOC Tours\09.-SEPTIEMBRE\16.- ALMACEN DE SACOS.pdf</filepath>
        <Paragraphs>10:00 HRS SEPTIEMBRE 16th , 2014FALTA RETIARAR SUPERSACOS DE RESIDUOS</Paragraphs>
      </itemcol>
      <itemcol>
        <word>2014FALTA</word>
        <filepath>\\192.168.2.2\00 - Departments\Common\SOC Cards\SOC Tours\09.-SEPTIEMBRE\18.-patio de tuberias strb.pdf</filepath>
        <Paragraphs>10:00 HRS SEPTIEMBRE 18th , 2014FALTA ORDEN Y LIMPIEZA EN EL AREA   </Paragraphs>
      </itemcol>
      <itemcol>
        <word>2014FALTA</word>
        <filepath>\\192.168.2.2\00 - Departments\Common\SOC Cards\SOC Tours\10.- OCTUBRE\19 Refrigerator Plant Room M202 .pdf</filepath>
        <Paragraphs>V    Safety Tour            Refrigerator Plant Room M202       22:00 HRS  OCT. 19TH, 2014FALTA SENALIZACION DE SUPERCIES CALIENTES</Paragraphs>
      </itemcol>
      <itemcol>
        <word>2014FALTA</word>
        <filepath>\\192.168.2.2\00 - Departments\Common\SOC Cards\SOC Tours\10.- OCTUBRE\23 Helideck Fire station .pdf</filepath>
        <Paragraphs>V  Safety Tour                   Helideck Fire station         22:00 HRS    OCT. 23rd, 2014FALTA ORDEN Y LIMPIEZA</Paragraphs>
      </itemcol>
      <itemcol>
        <word>2014FALTA</word>
        <filepath>\\192.168.2.2\00 - Departments\Common\SOC Cards\SOC Tours\10.- OCTUBRE\29 bahia de risers.pdf</filepath>
        <Paragraphs> HRS  OCT    h      FALTA ACORODNAMIENTOS EN AREA DE RIESGOS FALTA SEGREGACION ADECUADA  FALTAN  CHAVETAS QUE NOS GARANTIZEN UNA  </Paragraphs>
      </itemcol>
      <itemcol>
        <word>2014FALTA</word>
        <filepath>\\192.168.2.2\00 - Departments\Common\SOC Cards\SOC Tours\7.- July 2014\01 MUD PUMP ROOM 2014.pdf</filepath>
        <Paragraphs>V  Safety Tour                   MUD PUMP ROOM          22:00 HRS JULY 1st, 2014FALTA LIMPIEZA DE PASILLOS   </Paragraphs>
      </itemcol>
      <itemcol>
        <word>2014FALTA</word>
        <filepath>\\192.168.2.2\00 - Departments\Common\SOC Cards\SOC Tours\7.- July 2014\12 JULY 2014 SHAKER.pdf</filepath>
        <Paragraphs>V  Safety Tour                   SHAKER       10:00 HRS JULY 12 th  2014FALTA COLOCAR SE321ALAMIENTO DE SALIDA DE EMER-</Paragraphs>
      </itemcol>
      <itemcol>
        <word>2014FALTA</word>
        <filepath>\\192.168.2.2\00 - Departments\Common\SOC Cards\SOC Tours\7.- July 2014\14 RIG FLOOR.pdf</filepath>
        <Paragraphs>V  Safety Tour                   RIG FLOOR     22:00 HRS JULY 14 th  2014FALTA PROTECCION A CAMILLA AL INTERPERIE</Paragraphs>
      </itemcol>
      <itemcol>
        <word>2014FALTA</word>
        <filepath>\\192.168.2.2\00 - Departments\Common\SOC Cards\SOC Tours\7.- July 2014\19 JULY 2014 TORNO.pdf</filepath>
        <Paragraphs>V  Safety Tour                   TALLER DEL TORNO        10:00 HRS JULY 19 th  2014FALTA DE ORDEN Y7 LIMPIEZA</Paragraphs>
      </itemcol>
      <itemcol>
        <word>2014FALTA</word>
        <filepath>\\192.168.2.2\00 - Departments\Common\SOC Cards\SOC Tours\7.- July 2014\20 JULY 2014 UNIDAD DE ALTA.pdf</filepath>
        <Paragraphs>V  Safety Tour                   UNIDAD DE ALTA DE PRESION        10:00 HRS JULY 20 th  2014FALTA DE ORDEN Y  LIMPIEZA</Paragraphs>
      </itemcol>
      <itemcol>
        <word>2014FALTA</word>
        <filepath>\\192.168.2.2\00 - Departments\Common\SOC Cards\SOC Tours\7.- July 2014\24 Taller de soldadura.pdf</filepath>
        <Paragraphs>V  Safety Tour                   TALLER DE SOLDADURA 10:00 HRS JULY 24th  2014FALTA DE BASE Y LUGAR APROPIADO A  ENFRIADOR </Paragraphs>
      </itemcol>
      <itemcol>
        <word>2014FALTA</word>
        <filepath>\\192.168.2.2\00 - Departments\Common\SOC Cards\SOC Tours\8.-Agosto 2014\03 upper deck.pdf</filepath>
        <Paragraphs>V  Safety Tour                   UPPER DECK  10:00 HRS AUGUST 03 St, 2014FALTA ETIQUETAR  ANDAMIOS PARA IDENTIFICAR SI  ES SEGURO   </Paragraphs>
      </itemcol>
      <itemcol>
        <word>2014FALTA</word>
        <filepath>\\192.168.2.2\00 - Departments\Common\SOC Cards\SOC Tours\8.-Agosto 2014\28 Heavy tool store @ drill floor.pdf</filepath>
        <Paragraphs>V  Safety Tour              HEAVY TOOL STORE (DRILL FLOOR)        22:00 HRS AUGUST 28th , 2014FALTA IDENTIFICACION DE COLOR EN </Paragraphs>
      </itemcol>
    </collection>
  </value>
  <key>ROOM227FALTA</key>
  <value>
    <collection>
      <itemcol>
        <word>ROOM227FALTA</word>
        <filepath>\\192.168.2.2\00 - Departments\Common\scan\captain.3027\SOC Tours\2014\04.- ABRIL\13 ABRIL 2014 MOON POOL.pdf</filepath>
        <Paragraphs>FALTA DE ALMACENAMIENTO ADECUADO . PUMP ROOM227FALTA CADENAS DE PROTECCION PARA CAIDAS </Paragraphs>
      </itemcol>
    </collection>
  </value>
  <key>DOMESTICAFALTA</key>
  <value>
    <collection>
      <itemcol>
        <word>DOMESTICAFALTA</word>
        <filepath>\\192.168.2.2\00 - Departments\Common\scan\captain.3027\SOC Tours\2014\05.- MAYO\29 MAYO 2014  STORE.pdf</filepath>
        <Paragraphs>BASURA DOMESTICAFALTA COLOCAR  AVISO DE SEGURIDAD EN  </Paragraphs>
      </itemcol>
    </collection>
  </value>
  <key>FALLING</key>
  <value>
    <collection>
      <itemcol>
        <word>FALLING</word>
        <filepath>\\192.168.2.2\00 - Departments\Common\scan\captain.3027\SOC Tours\2014\06.- JUNIO\20 Jun Air Pressure Vessel Deck.pdf</filepath>
        <Paragraphs>FALLING OFF </Paragraphs>
      </itemcol>
      <itemcol>
        <word>FALLING</word>
        <filepath>\\192.168.2.2\00 - Departments\Common\scan\chiefofficer.3027\TRA 01\FORMATO VIEJO\TRA DE ALTURA NEW.docx</filepath>
        <Paragraphs> SCRAPES  CUTS  FALLING OBJECTS    M    L    L    EPP APROPIADO  PERSONAL CAPACITADO PARA REALIZAR LAS LABORES  USO DE ARNES  REATRACTIL  BANDAS CON G</Paragraphs>
      </itemcol>
      <itemcol>
        <word>FALLING</word>
        <filepath>\\192.168.2.2\00 - Departments\Common\scan\chiefofficer.3027\TRA 01\FORMATO VIEJO\TRA FUERA DE BORDA NEW.docx</filepath>
        <Paragraphs> EXPOSURE FRO M FALLING BODY OUTBOARD  SCRAPES CUTS  FALLING OBJECTS TO THE SEA     M    L    L    EPP APROPIADO  PERSONAL CAPACITADO PARA REALIZAR LA</Paragraphs>
      </itemcol>
    </collection>
  </value>
  <key>FALLET</key>
  <value>
    <collection>
      <itemcol>
        <word>FALLET</word>
        <filepath>\\192.168.2.2\00 - Departments\Common\scan\captain.3027\SOC Tours\2014\12. DICIEMBRE\27.- SHAKER ROOM.pdf</filepath>
        <Paragraphs>FALLET SIGNS  </Paragraphs>
      </itemcol>
    </collection>
  </value>
  <key>FALCON</key>
  <value>
    <collection>
      <itemcol>
        <word>FALCON</word>
        <filepath>\\192.168.2.2\00 - Departments\Common\scan\chiefofficer.3027\catalogo big country 2016.pdf</filepath>
        <Paragraphs>200784 99 ACCESORIOSDE VIAJE Y BICICLETAS ACC. VIAJE Y BICICLETASRACKS FALCON ACC. VIAJE Y BICICLETASRACKS TIPO ORIGINAL 760961RR</Paragraphs>
      </itemcol>
    </collection>
  </value>
  <key>PoleFALL</key>
  <value>
    <collection>
      <itemcol>
        <word>PoleFALL</word>
        <filepath>\\192.168.2.2\00 - Departments\Common\scan\RSTC.3027\Catalog\DBI-SALA-AN.pdf</filepath>
        <Paragraphs>isted Rescue by PoleFALL ARREST MODEAssisted Rescue by HandThese Assisted Rescue Options    Engage    the Descent Mode  </Paragraphs>
      </itemcol>
    </collection>
  </value>
  <key>en-USFALL</key>
  <value>
    <collection>
      <itemcol>
        <word>en-USFALL</word>
        <filepath>\\192.168.2.2\00 - Departments\Common\scan\RSTC.3027\Catalog\MSA-Catalogue.pdf</filepath>
        <Paragraphs>zard area       en USFALL PROTECTION EQUIPMENTen US shall be provided which prevents a fall  en US</Paragraphs>
      </itemcol>
    </collection>
  </value>
  <key>FALCONTM6m1016793EN</key>
  <value>
    <collection>
      <itemcol>
        <word>FALCONTM6m1016793EN</word>
        <filepath>\\192.168.2.2\00 - Departments\Common\scan\RSTC.3027\Catalog\slika~Honeywell Catalog 2013 2014.pdf</filepath>
        <Paragraphs>FALCONTM6m1016793EN 360</Paragraphs>
      </itemcol>
    </collection>
  </value>
  <key>FALLS</key>
  <value>
    <collection>
      <itemcol>
        <word>FALLS</word>
        <filepath>\\192.168.2.2\00 - Departments\Common\Share\313131\ELEVATORS&amp;SLIPS MANUALS\Black Jak Torque Master.pdf</filepath>
        <Paragraphs>ESSURE FALLS TO A LOW LEVEL </Paragraphs>
      </itemcol>
    </collection>
  </value>
  <key>AREAFALTA</key>
  <value>
    <collection>
      <itemcol>
        <word>AREAFALTA</word>
        <filepath>\\192.168.2.2\00 - Departments\Common\SOC Cards\SOC Tours\09.-SEPTIEMBRE\16.- ALMACEN DE SACOS.pdf</filepath>
        <Paragraphs>LACK OF HOUSEKEEPING IN OFFICE AREAFALTA ROMBO DE SEGURIDAD  EN BIDON </Paragraphs>
      </itemcol>
    </collection>
  </value>
  <key>18thFALTA</key>
  <value>
    <collection>
      <itemcol>
        <word>18thFALTA</word>
        <filepath>\\192.168.2.2\00 - Departments\Common\SOC Cards\SOC Tours\7.- July 2014\18 Area del Ancla de linea de perf..pdf</filepath>
        <Paragraphs>     HRS    JUL   thFALTA ORDEN Y LIMPIEZA  PISOS CON  CUBIETA ACEITOSA    </Paragraphs>
      </itemcol>
      <itemcol>
        <word>18thFALTA</word>
        <filepath>\\192.168.2.2\00 - Departments\Common\SOC Cards\SOC Tours\7.- July 2014\18 Sack Room.pdf</filepath>
        <Paragraphs>     HRS    JUl   thFALTA ORDEN Y LIMPIEZA  MATERIAL OBSTRUYENDO EQUIPO DE SEGURIDAD </Paragraphs>
      </itemcol>
    </collection>
  </value>
</dictionary>