<?xml version="1.0" encoding="utf-8" standalone="yes"?>
<dictionary>
  <key>AGIP</key>
  <value>
    <collection>
      <itemcol>
        <word>AGIP</word>
        <filepath>\\192.168.2.2\00 - Departments\Common\scan\chiefeng.3027\Mi Swaco 90-91-093 BEM 650-10T4.pdf</filepath>
      </itemcol>
    </collection>
  </value>
  <key>ACGIH</key>
  <value>
    <collection>
      <itemcol>
        <word>ACGIH</word>
        <filepath>\\192.168.2.2\00 - Departments\Common\scan\chiefeng.3027\Mi Swaco 90-91-093 BEM 650-10T4.pdf</filepath>
      </itemcol>
    </collection>
  </value>
  <key>ENGINEERING</key>
  <value>
    <collection>
      <itemcol>
        <word>ENGINEERING</word>
        <filepath>\\192.168.2.2\00 - Departments\Common\scan\chiefeng.3027\Mi Swaco 90-91-093 BEM 650-10T4.pdf</filepath>
      </itemcol>
      <itemcol>
        <word>ENGINEERING</word>
        <filepath>\\192.168.2.2\00 - Departments\Common\scan\chiefeng.3027\TCF - OEGU 209739-0.pdf</filepath>
      </itemcol>
    </collection>
  </value>
  <key>HYGIENIC</key>
  <value>
    <collection>
      <itemcol>
        <word>HYGIENIC</word>
        <filepath>\\192.168.2.2\00 - Departments\Common\scan\chiefeng.3027\Mi Swaco 90-91-093 BEM 650-10T4.pdf</filepath>
      </itemcol>
    </collection>
  </value>
  <key>TOXICOLOGICAL</key>
  <value>
    <collection>
      <itemcol>
        <word>TOXICOLOGICAL</word>
        <filepath>\\192.168.2.2\00 - Departments\Common\scan\chiefeng.3027\Mi Swaco 90-91-093 BEM 650-10T4.pdf</filepath>
      </itemcol>
    </collection>
  </value>
  <key>ECOLOGICAL</key>
  <value>
    <collection>
      <itemcol>
        <word>ECOLOGICAL</word>
        <filepath>\\192.168.2.2\00 - Departments\Common\scan\chiefeng.3027\Mi Swaco 90-91-093 BEM 650-10T4.pdf</filepath>
      </itemcol>
      <itemcol>
        <word>ECOLOGICAL</word>
        <filepath>\\192.168.2.2\00 - Departments\Common\scan\chiefeng.3027\TCF - OEGU 209739-0.pdf</filepath>
      </itemcol>
    </collection>
  </value>
  <key>CABLAGGI</key>
  <value>
    <collection>
      <itemcol>
        <word>CABLAGGI</word>
        <filepath>\\192.168.2.2\00 - Departments\Common\scan\chiefeng.3027\Mi Swaco 90-91-093 BEM 650-10T4.pdf</filepath>
      </itemcol>
    </collection>
  </value>
  <key>GIUNTI</key>
  <value>
    <collection>
      <itemcol>
        <word>GIUNTI</word>
        <filepath>\\192.168.2.2\00 - Departments\Common\scan\chiefeng.3027\Mi Swaco 90-91-093 BEM 650-10T4.pdf</filepath>
      </itemcol>
    </collection>
  </value>
  <key>GIUNTO</key>
  <value>
    <collection>
      <itemcol>
        <word>GIUNTO</word>
        <filepath>\\192.168.2.2\00 - Departments\Common\scan\chiefeng.3027\Mi Swaco 90-91-093 BEM 650-10T4.pdf</filepath>
      </itemcol>
    </collection>
  </value>
  <key>EQUIPAGGIATI</key>
  <value>
    <collection>
      <itemcol>
        <word>EQUIPAGGIATI</word>
        <filepath>\\192.168.2.2\00 - Departments\Common\scan\chiefeng.3027\Mi Swaco 90-91-093 BEM 650-10T4.pdf</filepath>
      </itemcol>
    </collection>
  </value>
  <key>REGIME</key>
  <value>
    <collection>
      <itemcol>
        <word>REGIME</word>
        <filepath>\\192.168.2.2\00 - Departments\Common\scan\chiefeng.3027\Mi Swaco 90-91-093 BEM 650-10T4.pdf</filepath>
      </itemcol>
    </collection>
  </value>
  <key>XICOLOGICAL</key>
  <value>
    <collection>
      <itemcol>
        <word>XICOLOGICAL</word>
        <filepath>\\192.168.2.2\00 - Departments\Common\scan\chiefeng.3027\TCF - OEGU 209739-0.pdf</filepath>
      </itemcol>
    </collection>
  </value>
</dictionary>